{"name":"preLoggingWithTaxRateRounded","id":"org.icrc.fadapplic.IRIS.FAD.AccountsPayable.PreRegistration:preLoggingWithTaxRateRounded","testCaseName":"org.icrc.fadapplic.IRIS.FAD.AccountsPayable.PreRegistration","testSteps":[{"number":1,"description":"Given that I\u0027m logged in to PreLogging page","duration":23815,"startTime":"2024-01-23T15:46:43.651+08:00[Asia/Shanghai]","screenshots":[{"screenshot":"4370ebb734b2d57f9dad264c35f5413e41c449c5740c0232be160972aa3cc8fc.png","timeStamp":1705996027466}],"result":"SUCCESS","precondition":false,"level":0,"children":[{"number":2,"description":"When i open FAD URL","duration":21827,"startTime":"2024-01-23T15:46:43.651+08:00[Asia/Shanghai]","screenshots":[{"screenshot":"28e37abbc4b19c7c749a95c94639fb111d616a6f7b4595f6c17d4e97c5c915ed.png","timeStamp":1705996025478}],"result":"SUCCESS","precondition":false,"level":1},{"number":3,"description":"When i open page from sidebar menu: {Accounts Payable,Pre-Registration,Pre-Logging}","duration":1981,"startTime":"2024-01-23T15:47:05.479+08:00[Asia/Shanghai]","screenshots":[{"screenshot":"28e37abbc4b19c7c749a95c94639fb111d616a6f7b4595f6c17d4e97c5c915ed.png","timeStamp":1705996025485},{"screenshot":"985000a6461b56c4921150a74a31ecb159a131c060889e39a1adc026b2d675d1.png","timeStamp":1705996026004},{"screenshot":"d3c7f06c5bedc3090f3a96cfcde4f5a7d01f457a9b4a348813b1be1f36469c3c.png","timeStamp":1705996026479},{"screenshot":"bd476af855dc77a6c5c8f7e1deb87bca38bea6e37940f9a008b631f32e930666.png","timeStamp":1705996026995},{"screenshot":"4370ebb734b2d57f9dad264c35f5413e41c449c5740c0232be160972aa3cc8fc.png","timeStamp":1705996027460}],"result":"SUCCESS","precondition":false,"level":1}]},{"number":4,"description":"Then the \u0027Payment Information\u0027 form and its contents should show up","duration":211,"startTime":"2024-01-23T15:47:07.466+08:00[Asia/Shanghai]","screenshots":[{"screenshot":"4370ebb734b2d57f9dad264c35f5413e41c449c5740c0232be160972aa3cc8fc.png","timeStamp":1705996027677}],"result":"SUCCESS","precondition":false,"level":0},{"number":5,"description":"When I set the \u0027Supplier\u0027 to \u0027SUE DRILLING\u0027","duration":5568,"startTime":"2024-01-23T15:47:07.678+08:00[Asia/Shanghai]","screenshots":[{"screenshot":"354cc80ef7211683470a70f62a6b68d04f020be31bfed66546847c7c529b3492.png","timeStamp":1705996030158},{"screenshot":"55d57cffea8ada52e6349766dc0ee4e9fe898db4f403b3509f5f2c936e7f3fda.png","timeStamp":1705996033246}],"result":"SUCCESS","precondition":false,"level":0},{"number":6,"description":"When I set the \u0027Invoice Number\u0027 to \u0027L8rikAyzE6\u0027","duration":522,"startTime":"2024-01-23T15:47:13.247+08:00[Asia/Shanghai]","screenshots":[{"screenshot":"6281f9f9fdec283b95d8f65938240cb835e5b7f14d9d35e631b08b75e483a529.png","timeStamp":1705996033769}],"result":"SUCCESS","precondition":false,"level":0},{"number":7,"description":"When I set the \u0027Currency\u0027 to \u0027USD\u0027","duration":8574,"startTime":"2024-01-23T15:47:13.770+08:00[Asia/Shanghai]","screenshots":[{"screenshot":"e0e50cb1205d67cf8158ccb13d6a7520c7119b992c8ee912955435c1562fb4af.png","timeStamp":1705996036934},{"screenshot":"6c477e9023a85f2ca98b50a00c404363f5ba4dcf4d05f2f619f17aee2c22c8ce.png","timeStamp":1705996042344}],"result":"SUCCESS","precondition":false,"level":0},{"number":8,"description":"When I click the \u0027Continue\u0027 button","duration":3066,"startTime":"2024-01-23T15:47:22.344+08:00[Asia/Shanghai]","screenshots":[{"screenshot":"5c456ca7197b8ad85d980effe7e4dc4569121bdd15a2571ed24b0ac68a0b05ea.png","timeStamp":1705996042770},{"screenshot":"91c7b889f77d813bb5094b8feed244bb63822eaecb3f80aecd2efb5ffeff004b.png","timeStamp":1705996045409}],"result":"SUCCESS","precondition":false,"level":0},{"number":9,"description":"When I select the first Bank Account and click \u0027Submit\u0027 button if modal exist","duration":45977,"startTime":"2024-01-23T15:47:25.410+08:00[Asia/Shanghai]","screenshots":[{"screenshot":"c171775e206ec0d30d50d320aa0a64b7cb76ea15e88a48533f2dedf38e74bde1.png","timeStamp":1705996076139},{"screenshot":"32690c60f81179f13e80a8d6ef6c3a385697f030ef1adb429118017c06d49fa7.png","timeStamp":1705996076605},{"screenshot":"95b9dc3eb0bccd2e1155d24c34935470d14aaf01ce5e98172bee3b5562688764.png","timeStamp":1705996091387}],"result":"SUCCESS","precondition":false,"level":0},{"number":10,"description":"Then the \u0027Payment Amount\u0027 form and Its contents should show up","duration":294,"startTime":"2024-01-23T15:48:11.387+08:00[Asia/Shanghai]","screenshots":[{"screenshot":"e9a4e8389208ce83723b63697a28f663741b729dae63b29e19c99667018de516.png","timeStamp":1705996091681}],"result":"SUCCESS","precondition":false,"level":0},{"number":11,"description":"When I set the \u0027Gross Amount\u0027 to \u00278909\u0027","duration":1052,"startTime":"2024-01-23T15:48:11.682+08:00[Asia/Shanghai]","screenshots":[{"screenshot":"92088fced90f81d08ef8310c44284ad063d9cff31583a1bc15500e25cf5156ca.png","timeStamp":1705996092734}],"result":"SUCCESS","precondition":false,"level":0},{"number":12,"description":"When I set the \u0027Tax Area\u0027 to \u0027KF11\u0027","duration":3003,"startTime":"2024-01-23T15:48:12.735+08:00[Asia/Shanghai]","screenshots":[{"screenshot":"59534413f8b99793747d197b246a5eceb60077cfb67320b041a6d1a7a6a46b27.png","timeStamp":1705996093355},{"screenshot":"186793488ad01ac864107179cdcdeeb460669c7636a68c5df4b42d126e2ce4a9.png","timeStamp":1705996094997},{"screenshot":"75198c56b3a940eda87f300afd576e7712366aa1b7c71299433edbe2d938e687.png","timeStamp":1705996095738}],"result":"SUCCESS","precondition":false,"level":0},{"number":13,"description":"When I set the \u0027Tax Amount\u0027 to \u00271400\u0027","duration":634,"startTime":"2024-01-23T15:48:15.738+08:00[Asia/Shanghai]","screenshots":[{"screenshot":"b525a2e62809fdc4cd691778d6e68afd33ae1898bb1c35eb733bdbdeb3b4d230.png","timeStamp":1705996096372}],"result":"SUCCESS","precondition":false,"level":0},{"number":14,"description":"When I click the \u0027Continue\u0027 button","duration":1297,"startTime":"2024-01-23T15:48:16.373+08:00[Asia/Shanghai]","screenshots":[{"screenshot":"218d54e04fadbdac8b04d9cf1337d95000ef065a6ae246e165d1ca629dedaa48.png","timeStamp":1705996096813},{"screenshot":"93789c37462adadb5a5fad687a33989f902d2461563ee56de039288688050145.png","timeStamp":1705996097670}],"result":"SUCCESS","precondition":false,"level":0},{"number":15,"description":"Then the \u0027Preliminary Distribution Account\u0027 modal and its contents should show up","duration":234,"startTime":"2024-01-23T15:48:17.671+08:00[Asia/Shanghai]","screenshots":[{"screenshot":"b191dc9e34409a9c85c5c4a7138b46f25dbd4644039b6962a96a038a05ecdb83.png","timeStamp":1705996097905}],"result":"SUCCESS","precondition":false,"level":0},{"number":16,"description":"When I set the modal \u0027Description\u0027 to \u0027TEST TAX RATE\u0027","duration":445,"startTime":"2024-01-23T15:48:17.906+08:00[Asia/Shanghai]","screenshots":[{"screenshot":"874ab96b562e8d95b3394a359b9cc182afeaa43d9a47de4b3553bf6b1e33d5e3.png","timeStamp":1705996098351}],"result":"SUCCESS","precondition":false,"level":0},{"number":17,"description":"When I click on \u0027Continue\u0027 button from modal","duration":2994,"startTime":"2024-01-23T15:48:18.351+08:00[Asia/Shanghai]","screenshots":[{"screenshot":"abfb7d30506281dc3452e18c4c0d669606292d12ee81e4d2a3810f7d67d5942b.png","timeStamp":1705996100084},{"screenshot":"7ed3fcabd2528254d42b2c0aff919663f48b1f0b86ae981a76c00ab634789961.png","timeStamp":1705996101345}],"result":"SUCCESS","precondition":false,"level":0},{"number":18,"description":"Then the \u0027Invoice Pre registration successfully created\u0027 modal should show up","duration":361,"startTime":"2024-01-23T15:48:21.345+08:00[Asia/Shanghai]","screenshots":[{"screenshot":"92a86fed8c6394c603c6152804dfd791fab2f70ace370708ca97c1439d7f4f0a.png","timeStamp":1705996101706}],"result":"SUCCESS","precondition":false,"level":0},{"number":19,"description":"When I click on \u0027Exit\u0027 button from modal","duration":586,"startTime":"2024-01-23T15:48:21.707+08:00[Asia/Shanghai]","screenshots":[{"screenshot":"3e03a72cf7750df74f2cf2309a54ee35ead9eb88f23ad29180e17405637453c1.png","timeStamp":1705996102285},{"screenshot":"3e03a72cf7750df74f2cf2309a54ee35ead9eb88f23ad29180e17405637453c1.png","timeStamp":1705996102293}],"result":"SUCCESS","precondition":false,"level":0},{"number":20,"description":"When I open the \u0027Batch Posting\u0027 page","duration":3809,"startTime":"2024-01-23T15:48:22.293+08:00[Asia/Shanghai]","screenshots":[{"screenshot":"48b491ef92a292445af93dd337301ec559dd50506e0b9a23b809d24c4a6e3c53.png","timeStamp":1705996106102}],"result":"SUCCESS","precondition":false,"level":0,"children":[{"number":21,"description":"When i open page from sidebar menu: {Batch Posting}","duration":3794,"startTime":"2024-01-23T15:48:22.299+08:00[Asia/Shanghai]","screenshots":[{"screenshot":"2dd4c6f10d7a7a06f40f8d2063ccfaa4656429728014a7c2425c6dc400c746b3.png","timeStamp":1705996102806},{"screenshot":"48b491ef92a292445af93dd337301ec559dd50506e0b9a23b809d24c4a6e3c53.png","timeStamp":1705996106093}],"result":"SUCCESS","precondition":false,"level":1}]},{"number":22,"description":"When I set the \u0027Batch Number\u0027 using the previously generated value from Pre registration modal","duration":465,"startTime":"2024-01-23T15:48:26.103+08:00[Asia/Shanghai]","screenshots":[{"screenshot":"006b80e07365c5fe4b483970b95994d5aa48c1429486afad44fd6840e2cb45cd.png","timeStamp":1705996106568}],"result":"SUCCESS","precondition":false,"level":0},{"number":23,"description":"When i clear the batch type field","duration":392,"startTime":"2024-01-23T15:48:26.568+08:00[Asia/Shanghai]","screenshots":[{"screenshot":"80ba763c28c6c27d26cbe0d7a347edc9ebce681788508ed2c797a206ddc32601.png","timeStamp":1705996106953},{"screenshot":"80ba763c28c6c27d26cbe0d7a347edc9ebce681788508ed2c797a206ddc32601.png","timeStamp":1705996106960}],"result":"SUCCESS","precondition":false,"level":0},{"number":24,"description":"When i click on search button","duration":1674,"startTime":"2024-01-23T15:48:26.960+08:00[Asia/Shanghai]","screenshots":[{"screenshot":"005032be4fbd12ffab67a2db73d676afd70ad6b8c932ae26f03581bc94ba7236.png","timeStamp":1705996107390},{"screenshot":"c6b3caf3b8c67b9eab376f7d647dd04b3654484cc5a42e2b0da92de154b981cb.png","timeStamp":1705996108634}],"result":"SUCCESS","precondition":false,"level":0},{"number":25,"description":"Then the batch posting search results should show up","duration":28,"startTime":"2024-01-23T15:48:28.635+08:00[Asia/Shanghai]","screenshots":[{"screenshot":"c6b3caf3b8c67b9eab376f7d647dd04b3654484cc5a42e2b0da92de154b981cb.png","timeStamp":1705996108663}],"result":"SUCCESS","precondition":false,"level":0},{"number":26,"description":"Then the post button of the first batch posting search result should be disabled","duration":209,"startTime":"2024-01-23T15:48:28.664+08:00[Asia/Shanghai]","screenshots":[{"screenshot":"c6b3caf3b8c67b9eab376f7d647dd04b3654484cc5a42e2b0da92de154b981cb.png","timeStamp":1705996108873}],"result":"SUCCESS","precondition":false,"level":0},{"number":27,"description":"When I click \u0027See More\u0027 button","duration":1708,"startTime":"2024-01-23T15:48:28.873+08:00[Asia/Shanghai]","screenshots":[{"screenshot":"accf4027b2fea33e8dc1acf242afba06a04b6d78599ca7108268c3f5b65a0b00.png","timeStamp":1705996109361},{"screenshot":"b36c79c1494a9984adfbea7474156e12859d647e066558a0aaad31169ccd9b88.png","timeStamp":1705996110581}],"result":"SUCCESS","precondition":false,"level":0},{"number":28,"description":"Then the post button of the first batch posting search result should be enabled","duration":212,"startTime":"2024-01-23T15:48:30.582+08:00[Asia/Shanghai]","screenshots":[{"screenshot":"01a693ce6c0901436f45bddbc835da8cfc0fa60f87b5bd9c7b23e78557db8be5.png","timeStamp":1705996110794}],"result":"SUCCESS","precondition":false,"level":0},{"number":29,"description":"When i click post button","duration":2338,"startTime":"2024-01-23T15:48:30.795+08:00[Asia/Shanghai]","screenshots":[{"screenshot":"d9bdd812ae94086e22b8998942e1738f478a626da6f52d54b82a91fd0f1305e2.png","timeStamp":1705996111193},{"screenshot":"423797cefc9db69a4470e0c3aa3a4699232f7ca66e70befa75a3a097c250a0b7.png","timeStamp":1705996111649},{"screenshot":"84ba569e0a6d01ae3d06948bd7396287794006cda4ddcccc2afac3bdfccbff49.png","timeStamp":1705996113133}],"result":"SUCCESS","precondition":false,"level":0},{"number":30,"description":"Then the \u0027Batch Successfully Posted\u0027 notification message should show up","duration":39,"startTime":"2024-01-23T15:48:33.133+08:00[Asia/Shanghai]","screenshots":[{"screenshot":"84ba569e0a6d01ae3d06948bd7396287794006cda4ddcccc2afac3bdfccbff49.png","timeStamp":1705996113172}],"result":"SUCCESS","precondition":false,"level":0}],"userStory":{"id":"org.icrc.fadapplic.IRIS.FAD.AccountsPayable.PreRegistration","storyName":"Pre registration","storyClassName":"org.icrc.fadapplic.IRIS.FAD.AccountsPayable.PreRegistration","path":"FAD.AccountsPayable","type":"story"},"featureTag":{"name":"Accounts payable/Pre registration","type":"story","displayName":"Accounts payable/Pre registration"},"title":"Pre logging with tax rate rounded","coreIssues":["VL03"],"tags":[{"name":"Accounts payable/Pre registration","type":"story","displayName":"Accounts payable/Pre registration"},{"name":"FAD/Accounts payable","type":"feature","displayName":"Accounts payable"},{"name":"FAD","type":"capability","displayName":"FAD"}],"startTime":"2024-01-23T15:46:43.389+08:00[Asia/Shanghai]","duration":109784,"projectKey":"","sessionId":"910907d156be17a8ccc3729ca2b5abe8","driver":"chrome","isManualTestingUpToDate":false,"manual":false,"testSource":"JUnit","result":"SUCCESS","issues":["VL03"]}