{"name":"preLoggingWithTaxRateRounded","id":"org.icrc.fadapplic.IRIS.FAD.AccountsPayable.PreRegistration:preLoggingWithTaxRateRounded","testCaseName":"org.icrc.fadapplic.IRIS.FAD.AccountsPayable.PreRegistration","testSteps":[{"number":1,"description":"Given that I\u0027m logged in to PreLogging page","duration":26942,"startTime":"2023-11-24T15:52:08.627+08:00[Asia/Shanghai]","screenshots":[{"screenshot":"23aa7417b3b9905a5558233be3e1c787cc91e8819b57a366918c263ee7656976.png","timeStamp":1700812355569}],"result":"SUCCESS","precondition":false,"level":0,"children":[{"number":2,"description":"When i open FAD URL","duration":24895,"startTime":"2023-11-24T15:52:08.627+08:00[Asia/Shanghai]","screenshots":[{"screenshot":"8fe90a153779251deab103d573f0e388475db0cd1ec6720c70504db21a5cafe3.png","timeStamp":1700812353522}],"result":"SUCCESS","precondition":false,"level":1},{"number":3,"description":"When i open page from sidebar menu: {Accounts Payable,Pre-Registration,Pre-Logging}","duration":2039,"startTime":"2023-11-24T15:52:33.523+08:00[Asia/Shanghai]","screenshots":[{"screenshot":"8fe90a153779251deab103d573f0e388475db0cd1ec6720c70504db21a5cafe3.png","timeStamp":1700812353530},{"screenshot":"3dcba0798314926f2273ecc15b75390a91d5a840e88bd24e29760b18253db5e3.png","timeStamp":1700812354048},{"screenshot":"93647ada313c7860b62a2231b0e1fb3416df7b5f8eed072f1a175b30db06ab5c.png","timeStamp":1700812354485},{"screenshot":"b91d71cd35a7b6ef7c76bc03dabfc284de473ca964479b52e74e9d599c397416.png","timeStamp":1700812354937},{"screenshot":"23aa7417b3b9905a5558233be3e1c787cc91e8819b57a366918c263ee7656976.png","timeStamp":1700812355562}],"result":"SUCCESS","precondition":false,"level":1}]},{"number":4,"description":"Then the \u0027Payment Information\u0027 form and its contents should show up","duration":226,"startTime":"2023-11-24T15:52:35.569+08:00[Asia/Shanghai]","screenshots":[{"screenshot":"23aa7417b3b9905a5558233be3e1c787cc91e8819b57a366918c263ee7656976.png","timeStamp":1700812355795}],"result":"SUCCESS","precondition":false,"level":0},{"number":5,"description":"When I set the \u0027Supplier\u0027 to \u0027SUE DRILLING\u0027","duration":4150,"startTime":"2023-11-24T15:52:35.796+08:00[Asia/Shanghai]","screenshots":[{"screenshot":"e1c65e23f8b726d2f5fc0d29c0135d9067e9856360f3d67bba4b75eee0488632.png","timeStamp":1700812358261},{"screenshot":"bc20100c483939ff2fbc8eeb879dd426660ed937ffdb6eb96d88f487d770231a.png","timeStamp":1700812359946}],"result":"SUCCESS","precondition":false,"level":0},{"number":6,"description":"When I set the \u0027Invoice Number\u0027 to \u00278UNyZL34sl\u0027","duration":470,"startTime":"2023-11-24T15:52:39.946+08:00[Asia/Shanghai]","screenshots":[{"screenshot":"ec6658325962d5c5afade73ccbefa7984962cbba5776601db84b8be91cfe2b31.png","timeStamp":1700812360416}],"result":"SUCCESS","precondition":false,"level":0},{"number":7,"description":"When I set the \u0027Currency\u0027 to \u0027USD\u0027","duration":6878,"startTime":"2023-11-24T15:52:40.417+08:00[Asia/Shanghai]","screenshots":[{"screenshot":"de7f06ab998bbeb9f9300f994147747c3ffabc05ea69d15f757fcab8725b8404.png","timeStamp":1700812363250},{"screenshot":"f38727526389f5d25977faaa638a237b35403e50d46542483f916e3439577d84.png","timeStamp":1700812367295}],"result":"SUCCESS","precondition":false,"level":0},{"number":8,"description":"When I click the \u0027Continue\u0027 button","duration":1429,"startTime":"2023-11-24T15:52:47.296+08:00[Asia/Shanghai]","screenshots":[{"screenshot":"bb88f3027766e53f76672ac077a78d9587e14a4b0da0fc6d47abff81730635f5.png","timeStamp":1700812367732},{"screenshot":"865b3b77ba66256d9961846f8491032227c687db93d412e38bd9de967aba8ac3.png","timeStamp":1700812368725}],"result":"SUCCESS","precondition":false,"level":0},{"number":9,"description":"When I select the first Bank Account and click \u0027Submit\u0027 button if modal exist","duration":32605,"startTime":"2023-11-24T15:52:48.726+08:00[Asia/Shanghai]","screenshots":[{"screenshot":"5d244a238b5ab2e43162e7ef9331e764d0d0fbd323f7d0db0cd612f77eb3d158.png","timeStamp":1700812399369},{"screenshot":"6a9b180a6520e60d5a9ea7fd1937ed98cc61b1d978e7b615071e8c14bb6e646f.png","timeStamp":1700812399838},{"screenshot":"0897bd257418935640ccbb79f5ac3344d6161d472eb8b5d890014d1bac21cbb7.png","timeStamp":1700812401331}],"result":"SUCCESS","precondition":false,"level":0},{"number":10,"description":"Then the \u0027Payment Amount\u0027 form and Its contents should show up","duration":239,"startTime":"2023-11-24T15:53:21.332+08:00[Asia/Shanghai]","screenshots":[{"screenshot":"2a0f9336463b6f23612e50e315aa366d224be398ea030bbb5eda9c6ac83fcef9.png","timeStamp":1700812401571}],"result":"SUCCESS","precondition":false,"level":0},{"number":11,"description":"When I set the \u0027Gross Amount\u0027 to \u00278909\u0027","duration":788,"startTime":"2023-11-24T15:53:21.571+08:00[Asia/Shanghai]","screenshots":[{"screenshot":"a7fe21b536345045bfe94b4bb08135e7411169fd163febc82285dec7ec323a50.png","timeStamp":1700812402358}],"result":"SUCCESS","precondition":false,"level":0},{"number":12,"description":"When I set the \u0027Tax Area\u0027 to \u0027KF11\u0027","duration":2918,"startTime":"2023-11-24T15:53:22.359+08:00[Asia/Shanghai]","screenshots":[{"screenshot":"a211b2e74e4a1fb2fab2e187228439a8da631088151b9c1fdc046d99d3465067.png","timeStamp":1700812402961},{"screenshot":"4c0692e24dfa90b75bc12980e4df05ce8df4316be112c1faaad6baa690d15a40.png","timeStamp":1700812404564},{"screenshot":"6fcca4991cd4a744ac65eb2cf5739bcf0cb267fb024dece3c085278e613c16e0.png","timeStamp":1700812405277}],"result":"SUCCESS","precondition":false,"level":0},{"number":13,"description":"When I set the \u0027Tax Amount\u0027 to \u00271400\u0027","duration":898,"startTime":"2023-11-24T15:53:25.277+08:00[Asia/Shanghai]","screenshots":[{"screenshot":"eadfc9eaef0b5b4152ed461579afae488c74ede71b7311a201a1a6c0a8b7520b.png","timeStamp":1700812406175}],"result":"SUCCESS","precondition":false,"level":0},{"number":14,"description":"When I click the \u0027Continue\u0027 button","duration":1413,"startTime":"2023-11-24T15:53:26.176+08:00[Asia/Shanghai]","screenshots":[{"screenshot":"a8778f2371ab261c677a6817df86a9b59a7d6c1d627801841a4407e5403b08a7.png","timeStamp":1700812406598},{"screenshot":"ae3fec69a1ec91eda414e55f3c2f159624623f5ee63a4a0d86d9476ed822bc0f.png","timeStamp":1700812407589}],"result":"SUCCESS","precondition":false,"level":0},{"number":15,"description":"Then the \u0027Preliminary Distribution Account\u0027 modal and its contents should show up","duration":231,"startTime":"2023-11-24T15:53:27.589+08:00[Asia/Shanghai]","screenshots":[{"screenshot":"76797bbedb65532ef26623090a3c0632c246ec9ead2c7a8fa3fe7fbc987e1800.png","timeStamp":1700812407820}],"result":"SUCCESS","precondition":false,"level":0},{"number":16,"description":"When I set the modal \u0027Description\u0027 to \u0027TEST TAX RATE\u0027","duration":464,"startTime":"2023-11-24T15:53:27.821+08:00[Asia/Shanghai]","screenshots":[{"screenshot":"93a411d37388600d7177880f7c697c8d11cda6cebea728b10bccdedd5b596b8c.png","timeStamp":1700812408285}],"result":"SUCCESS","precondition":false,"level":0},{"number":17,"description":"When I click on \u0027Continue\u0027 button from modal","duration":2751,"startTime":"2023-11-24T15:53:28.286+08:00[Asia/Shanghai]","screenshots":[{"screenshot":"bbaa934b1e4219695dfc2873847ee1664c8d39c70b1bad1aef5fa2934fa03627.png","timeStamp":1700812410018},{"screenshot":"d75c215b95961ff791aa818a39e085299341854fb90ac531956bf9005f387dc7.png","timeStamp":1700812411037}],"result":"SUCCESS","precondition":false,"level":0},{"number":18,"description":"Then the \u0027Invoice Pre registration successfully created\u0027 modal should show up","duration":322,"startTime":"2023-11-24T15:53:31.038+08:00[Asia/Shanghai]","screenshots":[{"screenshot":"fabf2d6b94372838ffb889ebcea927c58dd3ddd5ef354c65577065beab154f9c.png","timeStamp":1700812411360}],"result":"SUCCESS","precondition":false,"level":0},{"number":19,"description":"When I click on \u0027Exit\u0027 button from modal","duration":597,"startTime":"2023-11-24T15:53:31.361+08:00[Asia/Shanghai]","screenshots":[{"screenshot":"0925a46b6e2276f0055fbd4d58eb37870612c028a647672cbd89745b0a8280f5.png","timeStamp":1700812411951},{"screenshot":"0925a46b6e2276f0055fbd4d58eb37870612c028a647672cbd89745b0a8280f5.png","timeStamp":1700812411958}],"result":"SUCCESS","precondition":false,"level":0},{"number":20,"description":"When I open the \u0027Batch Posting\u0027 page","duration":3667,"startTime":"2023-11-24T15:53:31.958+08:00[Asia/Shanghai]","screenshots":[{"screenshot":"de647d11fdb485df642212ec0ebcf85305dc2b2f4fb1e5b876251feb54721e3e.png","timeStamp":1700812415625}],"result":"SUCCESS","precondition":false,"level":0,"children":[{"number":21,"description":"When i open page from sidebar menu: {Batch Posting}","duration":3654,"startTime":"2023-11-24T15:53:31.965+08:00[Asia/Shanghai]","screenshots":[{"screenshot":"5b22899dbec720a7ff3db903c43a3e90b78cc0b34118787898c3451098b386eb.png","timeStamp":1700812412440},{"screenshot":"de647d11fdb485df642212ec0ebcf85305dc2b2f4fb1e5b876251feb54721e3e.png","timeStamp":1700812415619}],"result":"SUCCESS","precondition":false,"level":1}]},{"number":22,"description":"When I set the \u0027Batch Number\u0027 using the previously generated value from Pre registration modal","duration":444,"startTime":"2023-11-24T15:53:35.626+08:00[Asia/Shanghai]","screenshots":[{"screenshot":"8d45e09e05ba9eae26cfa202fafa6c22d3991a0e13078f5be0f78b57849e3f3a.png","timeStamp":1700812416070}],"result":"SUCCESS","precondition":false,"level":0},{"number":23,"description":"When i clear the batch type field","duration":377,"startTime":"2023-11-24T15:53:36.071+08:00[Asia/Shanghai]","screenshots":[{"screenshot":"6562cbe47b6294af3cfede7042ddcd91453723e2fb9b60f4a84d1a38051db991.png","timeStamp":1700812416441},{"screenshot":"6562cbe47b6294af3cfede7042ddcd91453723e2fb9b60f4a84d1a38051db991.png","timeStamp":1700812416448}],"result":"SUCCESS","precondition":false,"level":0},{"number":24,"description":"When i click on search button","duration":1661,"startTime":"2023-11-24T15:53:36.448+08:00[Asia/Shanghai]","screenshots":[{"screenshot":"2785d4476b63b1c8bec8ae254de709e99253b40d56c2ea809d281d53328da410.png","timeStamp":1700812416890},{"screenshot":"0c25a99197bad2f38d79fb7e243719714d159820a70f1ba38ba12ebbf9f02da0.png","timeStamp":1700812418109}],"result":"SUCCESS","precondition":false,"level":0},{"number":25,"description":"Then the batch posting search results should show up","duration":42,"startTime":"2023-11-24T15:53:38.109+08:00[Asia/Shanghai]","screenshots":[{"screenshot":"0c25a99197bad2f38d79fb7e243719714d159820a70f1ba38ba12ebbf9f02da0.png","timeStamp":1700812418151}],"result":"SUCCESS","precondition":false,"level":0},{"number":26,"description":"Then the post button of the first batch posting search result should be disabled","duration":225,"startTime":"2023-11-24T15:53:38.152+08:00[Asia/Shanghai]","screenshots":[{"screenshot":"0c25a99197bad2f38d79fb7e243719714d159820a70f1ba38ba12ebbf9f02da0.png","timeStamp":1700812418377}],"result":"SUCCESS","precondition":false,"level":0},{"number":27,"description":"When I click \u0027See More\u0027 button","duration":1650,"startTime":"2023-11-24T15:53:38.378+08:00[Asia/Shanghai]","screenshots":[{"screenshot":"a4811d17ccc3fe6520c8d51ad70d2264e6a85cb8a4e9d8458ea5c39187566a6f.png","timeStamp":1700812418812},{"screenshot":"b37631db2e66fa0c59a0a8f82894c6445a726af714dcc51ad145269498647471.png","timeStamp":1700812420028}],"result":"SUCCESS","precondition":false,"level":0},{"number":28,"description":"Then the post button of the first batch posting search result should be enabled","duration":221,"startTime":"2023-11-24T15:53:40.029+08:00[Asia/Shanghai]","screenshots":[{"screenshot":"1ba71deb08b030ba8019ac4c4caf7e3f8410331b85b308e214902271ce74d57b.png","timeStamp":1700812420250}],"result":"SUCCESS","precondition":false,"level":0},{"number":29,"description":"When i click post button","duration":2196,"startTime":"2023-11-24T15:53:40.250+08:00[Asia/Shanghai]","screenshots":[{"screenshot":"ed1cee33ce1a7a61d5ca7915c0033f127f7a62e3a43a990c097563fa1eec2e61.png","timeStamp":1700812420646},{"screenshot":"293ba723ab863ff62fb892f572d1715643441d2bf027ea3bc4cd7bbb6ad3b003.png","timeStamp":1700812421099},{"screenshot":"2654072492fe1ff56de46c309d05188ee25a99b75cabc8b496216678f54cc834.png","timeStamp":1700812422446}],"result":"SUCCESS","precondition":false,"level":0},{"number":30,"description":"Then the \u0027Batch Successfully Posted\u0027 notification message should show up","duration":44,"startTime":"2023-11-24T15:53:42.447+08:00[Asia/Shanghai]","screenshots":[{"screenshot":"2654072492fe1ff56de46c309d05188ee25a99b75cabc8b496216678f54cc834.png","timeStamp":1700812422491}],"result":"SUCCESS","precondition":false,"level":0}],"userStory":{"id":"org.icrc.fadapplic.IRIS.FAD.AccountsPayable.PreRegistration","storyName":"Pre registration","storyClassName":"org.icrc.fadapplic.IRIS.FAD.AccountsPayable.PreRegistration","path":"FAD.AccountsPayable","type":"story"},"featureTag":{"name":"Accounts payable/Pre registration","type":"story","displayName":"Accounts payable/Pre registration"},"title":"Pre logging with tax rate rounded","coreIssues":["VL03"],"tags":[{"name":"Accounts payable/Pre registration","type":"story","displayName":"Pre registration"},{"name":"FAD/Accounts payable","type":"feature","displayName":"Accounts payable"},{"name":"FAD","type":"capability","displayName":"FAD"}],"startTime":"2023-11-24T15:52:08.391+08:00[Asia/Shanghai]","duration":94100,"projectKey":"","sessionId":"b7c7a479c0017b6fe3a0c3bef112074b","driver":"chrome","isManualTestingUpToDate":false,"manual":false,"testSource":"JUnit","result":"SUCCESS","issues":["VL03"]}