{"name":"createVoucherEntryAndEdit","id":"org.icrc.fadapplic.IRIS.FAD.AccountsPayable.ReviewAPEntries:createVoucherEntryAndEdit","testCaseName":"org.icrc.fadapplic.IRIS.FAD.AccountsPayable.ReviewAPEntries","testSteps":[{"number":1,"description":"Given that I\u0027m logged in to Voucher Entry page","duration":31794,"startTime":"2023-11-24T16:14:16.208+08:00[Asia/Shanghai]","screenshots":[{"screenshot":"f3b349aeb415ea0962c4bdea9dd84618d93864139a5b6eafec7193511a091f9c.png","timeStamp":1700813688002}],"result":"SUCCESS","precondition":false,"level":0,"children":[{"number":2,"description":"When i open FAD URL","duration":29754,"startTime":"2023-11-24T16:14:16.209+08:00[Asia/Shanghai]","screenshots":[{"screenshot":"68c0fd7b88de2dcca4919f47c8e92ac5b355037e99ce4cbcae6c6e96e46745a8.png","timeStamp":1700813685963}],"result":"SUCCESS","precondition":false,"level":1},{"number":3,"description":"When i open page from sidebar menu: {Accounts Payable,Voucher Entries,Voucher Entry}","duration":2031,"startTime":"2023-11-24T16:14:45.965+08:00[Asia/Shanghai]","screenshots":[{"screenshot":"68c0fd7b88de2dcca4919f47c8e92ac5b355037e99ce4cbcae6c6e96e46745a8.png","timeStamp":1700813685970},{"screenshot":"a5c7272b9c870cdadb539f8abb7bc441d5bafb588cbc3478ad24963b7f8a9f0a.png","timeStamp":1700813686458},{"screenshot":"7cb291263f3f271716c415469bbc402ec685bc0104e7f5e817c143e18b30ce2c.png","timeStamp":1700813686904},{"screenshot":"7ce512f6719b893a4ebd74544c16443ae90c3b63d22a818554fc6f02f3db5625.png","timeStamp":1700813687397},{"screenshot":"f3b349aeb415ea0962c4bdea9dd84618d93864139a5b6eafec7193511a091f9c.png","timeStamp":1700813687996}],"result":"SUCCESS","precondition":false,"level":1}]},{"number":4,"description":"Then the Payment Information form and its contents should show up","duration":272,"startTime":"2023-11-24T16:14:48.002+08:00[Asia/Shanghai]","screenshots":[{"screenshot":"f3b349aeb415ea0962c4bdea9dd84618d93864139a5b6eafec7193511a091f9c.png","timeStamp":1700813688274}],"result":"SUCCESS","precondition":false,"level":0},{"number":5,"description":"When I set the Supplier to \u0027118173\u0027","duration":3600,"startTime":"2023-11-24T16:14:48.275+08:00[Asia/Shanghai]","screenshots":[{"screenshot":"63475ac9bad2a1d769145468be6ee3f0a9300f3efc53446b1e6c75dfeef1dc53.png","timeStamp":1700813690177},{"screenshot":"ff588189d30ac60bc80ea7a1d13e078fee0f8bddb68927f744c8f40b662c8cee.png","timeStamp":1700813691875}],"result":"SUCCESS","precondition":false,"level":0},{"number":6,"description":"When I set the \u0027Invoice Number\u0027 to \u0027sXEptAT8gk\u0027","duration":484,"startTime":"2023-11-24T16:14:51.876+08:00[Asia/Shanghai]","screenshots":[{"screenshot":"e0f33fa309a00c61f6189d8ee610b2e65f658178d84c969823d8b572e82f10f4.png","timeStamp":1700813692360}],"result":"SUCCESS","precondition":false,"level":0},{"number":7,"description":"When I set the Currency to \u0027USD\u0027","duration":3814,"startTime":"2023-11-24T16:14:52.360+08:00[Asia/Shanghai]","screenshots":[{"screenshot":"f086835f7c424492908b33019f8dbea05c469a7da18036318b840db3cbb772b3.png","timeStamp":1700813695184},{"screenshot":"bb71267f9a9490b167932a2530e5dfb4e1124c66f05116d02dbf0bb46d1912b2.png","timeStamp":1700813696174}],"result":"SUCCESS","precondition":false,"level":0},{"number":8,"description":"When i click on continue button","duration":1365,"startTime":"2023-11-24T16:14:56.175+08:00[Asia/Shanghai]","screenshots":[{"screenshot":"375a9fd84f669737b029295ed2fbbe606bb68cf77d8a1e6473e32ca5acb7d2a0.png","timeStamp":1700813696601},{"screenshot":"961ab241a92deadf60b09805454cbc770881ea792f9676abae298cbfe8e4c469.png","timeStamp":1700813697540}],"result":"SUCCESS","precondition":false,"level":0},{"number":9,"description":"When I select the first Bank Account and click \u0027Submit\u0027 button if modal exist","duration":32636,"startTime":"2023-11-24T16:14:57.541+08:00[Asia/Shanghai]","screenshots":[{"screenshot":"743adf7c71339123139eecf6aebf9ac5507d45f4b74f5238a3045df07fea973d.png","timeStamp":1700813728215},{"screenshot":"a22ae3d31c07cd0a8e377700fc8e6d5209ccba7c6bb2c012b860267db2e72702.png","timeStamp":1700813728684},{"screenshot":"75ef09979a6467fec53ebcba39f1731d3f0461e973e577458431000b3ee14091.png","timeStamp":1700813730177}],"result":"SUCCESS","precondition":false,"level":0},{"number":10,"description":"When I set the Gross Amount to \u002710000\u0027","duration":3559,"startTime":"2023-11-24T16:15:30.178+08:00[Asia/Shanghai]","screenshots":[{"screenshot":"39a566f9fec4fb65d2a828e6b3a48ef54dc21f5419b992df1da186fe6fcc3253.png","timeStamp":1700813733737}],"result":"SUCCESS","precondition":false,"level":0},{"number":11,"description":"When i click on continue button","duration":2635,"startTime":"2023-11-24T16:15:33.738+08:00[Asia/Shanghai]","screenshots":[{"screenshot":"d4b1f3664b0e3dbd2453c0ae7ece307c4c714800c37abd14a5c0b703f5eb5dc1.png","timeStamp":1700813734158},{"screenshot":"9f55183d73b0f00f4a951c0f9fb3b38b75ec926a9d597f48195e2de71b86f42d.png","timeStamp":1700813736373}],"result":"SUCCESS","precondition":false,"level":0},{"number":12,"description":"Then the \u0027GL Distribution\u0027 form and its contents should show up","duration":219,"startTime":"2023-11-24T16:15:36.373+08:00[Asia/Shanghai]","screenshots":[{"screenshot":"622a48e031c06e4d5a3fe1f23298691d5607cda50910737de6a05ff82e982ced.png","timeStamp":1700813736592}],"result":"SUCCESS","precondition":false,"level":0},{"number":13,"description":"When I set the Account Number to \u002791100\u0027","duration":6431,"startTime":"2023-11-24T16:15:36.592+08:00[Asia/Shanghai]","screenshots":[{"screenshot":"d3af0f2979cc132a896f01e77f239255514e3f162c362802ef732df7ed4e97d1.png","timeStamp":1700813738579},{"screenshot":"13ac6d0928025491887a1b2a2b80e0376ead111f7e75c5dc80e5c300d08aefa2.png","timeStamp":1700813743023}],"result":"SUCCESS","precondition":false,"level":0},{"number":14,"description":"When I set the Line Description to \u0027Test\u0027","duration":599,"startTime":"2023-11-24T16:15:43.024+08:00[Asia/Shanghai]","screenshots":[{"screenshot":"762e4320e713609092a146583c8fbb87f184c454a3bd974ff6b29b44af82c16d.png","timeStamp":1700813743623}],"result":"SUCCESS","precondition":false,"level":0},{"number":15,"description":"When I set the Amount to \u002710000\u0027","duration":3966,"startTime":"2023-11-24T16:15:43.624+08:00[Asia/Shanghai]","screenshots":[{"screenshot":"3acdab587fa97b7682566ebbe7062163e35b43bfd33a29f1e0531b960f507cee.png","timeStamp":1700813747590}],"result":"SUCCESS","precondition":false,"level":0},{"number":16,"description":"When I set the Employee to \u0027Milos Vitas\u0027","duration":8432,"startTime":"2023-11-24T16:15:47.591+08:00[Asia/Shanghai]","screenshots":[{"screenshot":"4afe5bf5636babcd8171f039fa13f38511f0a824e513ffb397b50528416dd473.png","timeStamp":1700813750561},{"screenshot":"242f18a5fb89472d18f08deea8680a7d45499fec4ba2db8e3b734888dcb5551d.png","timeStamp":1700813756022}],"result":"SUCCESS","precondition":false,"level":0},{"number":17,"description":"When I set the Cost Center to \u00271MAN400\u0027","duration":3151,"startTime":"2023-11-24T16:15:56.023+08:00[Asia/Shanghai]","screenshots":[{"screenshot":"c7526856bedc48530bfc5be5bf3f2d4b6884428087480c616483494318a43791.png","timeStamp":1700813758091},{"screenshot":"4da6c77acfd3f85ec8249c6eb6cf484a27ffe775a8df9527effa73fc6c8ba422.png","timeStamp":1700813759174}],"result":"SUCCESS","precondition":false,"level":0},{"number":18,"description":"When I set the General Obj to \u0027AFGHAI\u0027","duration":3682,"startTime":"2023-11-24T16:15:59.175+08:00[Asia/Shanghai]","screenshots":[{"screenshot":"8f38a632ad899f450d445235b26105a9b30049ce839074f09e761176dc5ef4c8.png","timeStamp":1700813761774},{"screenshot":"b35a7b23112e23674fe32fb44a1ff9d77a2051348da5a2ce0e487cc9b96c354e.png","timeStamp":1700813762857}],"result":"SUCCESS","precondition":false,"level":0},{"number":19,"description":"When I click on the \u0027Show Next\u0027 button","duration":441,"startTime":"2023-11-24T16:16:02.858+08:00[Asia/Shanghai]","screenshots":[{"screenshot":"cd370ca263c4b98f66b7f31e521ddfc306a37b8bb95399491cb1904e5ee68ab5.png","timeStamp":1700813763291},{"screenshot":"cd370ca263c4b98f66b7f31e521ddfc306a37b8bb95399491cb1904e5ee68ab5.png","timeStamp":1700813763299}],"result":"SUCCESS","precondition":false,"level":0},{"number":20,"description":"When I set the AOE to \u0027YAO\u0027","duration":3172,"startTime":"2023-11-24T16:16:03.300+08:00[Asia/Shanghai]","screenshots":[{"screenshot":"7f8eecdaf21dfc789bfb0ed231c660440cc12a6b132a4a916a3e48c27d1f4b2c.png","timeStamp":1700813765372},{"screenshot":"2df89df82bd72a67ee0eac62e832bb9edacab9029657493a3af5fd9cae0998cb.png","timeStamp":1700813766472}],"result":"SUCCESS","precondition":false,"level":0},{"number":21,"description":"When I set the Line Ref to \u0027Test123\u0027","duration":701,"startTime":"2023-11-24T16:16:06.472+08:00[Asia/Shanghai]","screenshots":[{"screenshot":"3a7de970cb0e589e99b305a9c1d46a9176ba36c08101fdc06ee2a710f799d257.png","timeStamp":1700813767173}],"result":"SUCCESS","precondition":false,"level":0},{"number":22,"description":"When I set the Purchase Order to \u002712345\u0027","duration":598,"startTime":"2023-11-24T16:16:07.174+08:00[Asia/Shanghai]","screenshots":[{"screenshot":"ffc7f2def9e89726092e739449d52adbafb70107ffc766453885d855bdc1868b.png","timeStamp":1700813767772}],"result":"SUCCESS","precondition":false,"level":0},{"number":23,"description":"When I set the Units to \u002710\u0027","duration":633,"startTime":"2023-11-24T16:16:07.773+08:00[Asia/Shanghai]","screenshots":[{"screenshot":"0c9a0fcea42344a9fbefd42cbfd66a94c595b6c5af3bf798c295ae201270cac3.png","timeStamp":1700813768406}],"result":"SUCCESS","precondition":false,"level":0},{"number":24,"description":"When I set the Unit of Measure to \u002710\u0027","duration":3207,"startTime":"2023-11-24T16:16:08.407+08:00[Asia/Shanghai]","screenshots":[{"screenshot":"389ce5df689026436bd49841da3c2289797b041c805e472eb49d409bbf606bb7.png","timeStamp":1700813770478},{"screenshot":"04b0bffb1251e7b8e973746582e500663593f7fe455e60a64eb0bab7c172ec64.png","timeStamp":1700813771614}],"result":"SUCCESS","precondition":false,"level":0},{"number":25,"description":"When I click on \u0027Save\u0027 button","duration":1725,"startTime":"2023-11-24T16:16:11.615+08:00[Asia/Shanghai]","screenshots":[{"screenshot":"61535d137e3d6ea8a7eef8c9b9e015f1124e720b0e0ce9f0ca30402c8e1388de.png","timeStamp":1700813772103},{"screenshot":"27a6dd33edcdeab597a88d971edda615dd091fc37f30e9dd551d290ddc603e0d.png","timeStamp":1700813773340}],"result":"SUCCESS","precondition":false,"level":0},{"number":26,"description":"Then the voucher entry successfully created modal and its contents should show up","duration":765,"startTime":"2023-11-24T16:16:13.341+08:00[Asia/Shanghai]","screenshots":[{"screenshot":"578d88b2663fd2ac0eb7b480a273a96a650cdfc3765f93475678bf58dc7f68e8.png","timeStamp":1700813774106}],"result":"SUCCESS","precondition":false,"level":0,"children":[{"number":27,"description":"Then the voucher entry successfully created modal should show up","duration":246,"startTime":"2023-11-24T16:16:13.347+08:00[Asia/Shanghai]","screenshots":[{"screenshot":"e6aed394eed0e35ed410ea2fa3a2daf9204d4848391847f3f7b0646305217ff7.png","timeStamp":1700813773592}],"result":"SUCCESS","precondition":false,"level":1},{"number":28,"description":"Then the batch number from voucher entry successfully created modal should show up","duration":278,"startTime":"2023-11-24T16:16:13.593+08:00[Asia/Shanghai]","screenshots":[{"screenshot":"e6aed394eed0e35ed410ea2fa3a2daf9204d4848391847f3f7b0646305217ff7.png","timeStamp":1700813773601},{"screenshot":"c7f61b081b5108599370ca893f0d1df4a28e8549ec1d8f825acf27e53e572511.png","timeStamp":1700813773871}],"result":"SUCCESS","precondition":false,"level":1},{"number":29,"description":"Then the document number from voucher entry successfully created modal should show up","duration":227,"startTime":"2023-11-24T16:16:13.872+08:00[Asia/Shanghai]","screenshots":[{"screenshot":"c7f61b081b5108599370ca893f0d1df4a28e8549ec1d8f825acf27e53e572511.png","timeStamp":1700813773878},{"screenshot":"578d88b2663fd2ac0eb7b480a273a96a650cdfc3765f93475678bf58dc7f68e8.png","timeStamp":1700813774099}],"result":"SUCCESS","precondition":false,"level":1}]},{"number":30,"description":"Given that I\u0027m logged into \u0027Voucher Entry Review\u0027 page","duration":12339,"startTime":"2023-11-24T16:16:14.107+08:00[Asia/Shanghai]","screenshots":[{"screenshot":"d17f26e18e3a7842d8fcbb8430a66aeb8f34517732e5b1de550a3f0cac82b3ac.png","timeStamp":1700813786446}],"result":"SUCCESS","precondition":false,"level":0,"children":[{"number":31,"description":"When i open FAD URL","duration":7630,"startTime":"2023-11-24T16:16:14.113+08:00[Asia/Shanghai]","screenshots":[{"screenshot":"d57da33ab28a7737552b817515b7995470f0148e325aed720f8288d59121ea7c.png","timeStamp":1700813781743}],"result":"SUCCESS","precondition":false,"level":1},{"number":32,"description":"When i open page from sidebar menu: {Accounts Payable,Review A/P Entries,Voucher Entries}","duration":4692,"startTime":"2023-11-24T16:16:21.744+08:00[Asia/Shanghai]","screenshots":[{"screenshot":"d57da33ab28a7737552b817515b7995470f0148e325aed720f8288d59121ea7c.png","timeStamp":1700813781750},{"screenshot":"0b9d01dc0604b2920d052c457eeb46ae3e5c94c1c03472bad9188610ac8f1a1e.png","timeStamp":1700813782259},{"screenshot":"0bed9fb998f1322b5ec037d8a91d9619a34a16a4d72343dbb4e5417093d87c26.png","timeStamp":1700813782732},{"screenshot":"787e90268d2414d19f0a512a9f41270509c2ea3f552cb48f9a4d068b903dfcd5.png","timeStamp":1700813783206},{"screenshot":"d17f26e18e3a7842d8fcbb8430a66aeb8f34517732e5b1de550a3f0cac82b3ac.png","timeStamp":1700813786436}],"result":"SUCCESS","precondition":false,"level":1}]},{"number":33,"description":"Then the \u0027Voucher Entry Review\u0027 page and its contents should show up","duration":248,"startTime":"2023-11-24T16:16:26.446+08:00[Asia/Shanghai]","screenshots":[{"screenshot":"d17f26e18e3a7842d8fcbb8430a66aeb8f34517732e5b1de550a3f0cac82b3ac.png","timeStamp":1700813786694}],"result":"SUCCESS","precondition":false,"level":0},{"number":34,"description":"When I set the \u0027Batch Number\u0027 using saved value","duration":521,"startTime":"2023-11-24T16:16:26.694+08:00[Asia/Shanghai]","screenshots":[{"screenshot":"1a5dee40060a7f5a822e67ffc158a1234dc4dc0b15d91a7cae1295039892d2bb.png","timeStamp":1700813787215}],"result":"SUCCESS","precondition":false,"level":0},{"number":35,"description":"When I click on \u0027Search\u0027 button","duration":1297,"startTime":"2023-11-24T16:16:27.216+08:00[Asia/Shanghai]","screenshots":[{"screenshot":"086804485956d17aff363a11937f2b3fcd9ea496e597c10a192ca4d275c5e6d1.png","timeStamp":1700813787680},{"screenshot":"22e8007c758a918198e78a463262061c8939503dbc8fa6e91ae202ddbb65fdce.png","timeStamp":1700813788513}],"result":"SUCCESS","precondition":false,"level":0},{"number":36,"description":"Then the \u0027Review Voucher\u0027 search result should show up","duration":26,"startTime":"2023-11-24T16:16:28.513+08:00[Asia/Shanghai]","screenshots":[{"screenshot":"22e8007c758a918198e78a463262061c8939503dbc8fa6e91ae202ddbb65fdce.png","timeStamp":1700813788539}],"result":"SUCCESS","precondition":false,"level":0},{"number":37,"description":"When I select the first voucher entry","duration":463,"startTime":"2023-11-24T16:16:28.540+08:00[Asia/Shanghai]","screenshots":[{"screenshot":"481782331f75ea8d83f294d134a8aeae5e872ad694230f5aa8fc4f8b6b86ceff.png","timeStamp":1700813788996},{"screenshot":"481782331f75ea8d83f294d134a8aeae5e872ad694230f5aa8fc4f8b6b86ceff.png","timeStamp":1700813789003}],"result":"SUCCESS","precondition":false,"level":0},{"number":38,"description":"When I click on \u0027Edit\u0027 button","duration":1984,"startTime":"2023-11-24T16:16:29.003+08:00[Asia/Shanghai]","screenshots":[{"screenshot":"a4b68f02cccc45b9dced7ea4181860f7e29ae53583520a9c656610d437f89e55.png","timeStamp":1700813789415},{"screenshot":"96c7faa52a094669d1d7b042efa3d59245ec63cc72d1e110ff4ba60e1d642398.png","timeStamp":1700813790987}],"result":"SUCCESS","precondition":false,"level":0},{"number":39,"description":"When I click \u0027Payment Amount\u0027 button","duration":454,"startTime":"2023-11-24T16:16:30.988+08:00[Asia/Shanghai]","screenshots":[{"screenshot":"bf7e78edc054db25b59e24b2d92d027801743b83bcb78d59c4e13d2770ec2882.png","timeStamp":1700813791435},{"screenshot":"bf7e78edc054db25b59e24b2d92d027801743b83bcb78d59c4e13d2770ec2882.png","timeStamp":1700813791442}],"result":"SUCCESS","precondition":false,"level":0},{"number":40,"description":"Then the \u0027Payment Amount\u0027 form should show up","duration":245,"startTime":"2023-11-24T16:16:31.443+08:00[Asia/Shanghai]","screenshots":[{"screenshot":"1bb5b38b1d439aaa3320ba3f4e790b15e7ba96676c2c6248ab333d14762125e7.png","timeStamp":1700813791688}],"result":"SUCCESS","precondition":false,"level":0},{"number":41,"description":"When I set the Gross Amount to \u00271500\u0027","duration":1164,"startTime":"2023-11-24T16:16:31.689+08:00[Asia/Shanghai]","screenshots":[{"screenshot":"c82b6b6322cc57871683f20c90367f6df690bac3d50a791d6d708af255ba5756.png","timeStamp":1700813792072},{"screenshot":"080309eecbc09b3888b6c7f77ce7ded5c45513f32405d8fbcc89bca1fee7dd74.png","timeStamp":1700813792853}],"result":"SUCCESS","precondition":false,"level":0},{"number":42,"description":"When I click on \u0027Continue\u0027 button","duration":1517,"startTime":"2023-11-24T16:16:32.854+08:00[Asia/Shanghai]","screenshots":[{"screenshot":"28e95e70f1bb9d75aa51b8eb2b310bd66ed11c1bb5f4fdcdbb28784abb467934.png","timeStamp":1700813793290},{"screenshot":"156bce61773ad985a2d6d81f589e399044aed28d55d0e6cc832cb6257c618a25.png","timeStamp":1700813794371}],"result":"SUCCESS","precondition":false,"level":0},{"number":43,"description":"Then the \u0027GL Distribution\u0027 form should show up","duration":217,"startTime":"2023-11-24T16:16:34.371+08:00[Asia/Shanghai]","screenshots":[{"screenshot":"edc2ed93a0c42d681fe1978df97f52599b63e8e743b907db99d627b696c64008.png","timeStamp":1700813794588}],"result":"SUCCESS","precondition":false,"level":0},{"number":44,"description":"When I set the Account Number to \u0027212100\u0027","duration":3484,"startTime":"2023-11-24T16:16:34.589+08:00[Asia/Shanghai]","screenshots":[{"screenshot":"1a07d7a818c1446350027cde5374777001d1fba4fff5b450bd35594d8690f08c.png","timeStamp":1700813795023},{"screenshot":"7a745f47b3eef30d9bc81cd082033a45f350b3d575f07db90a06f9d95fcbb277.png","timeStamp":1700813796978},{"screenshot":"e167e5943ea6c26adf19eb4d7e6081701f49707b9abe4927fd2ecffab18236ed.png","timeStamp":1700813798073}],"result":"SUCCESS","precondition":false,"level":0},{"number":45,"description":"When I set the Amount to \u00271500\u0027","duration":951,"startTime":"2023-11-24T16:16:38.073+08:00[Asia/Shanghai]","screenshots":[{"screenshot":"2fccf15519b38781f29438e6c5b49586ee00652854d23760dde98bad34dd0a25.png","timeStamp":1700813798476},{"screenshot":"d19ee8cf7113b1e0964caa5bf55abe6ab1471853f36b5c4af1c111017f0c9b33.png","timeStamp":1700813799024}],"result":"SUCCESS","precondition":false,"level":0},{"number":46,"description":"When I set the Cost Center to \u0027KYI2100\u0027","duration":4231,"startTime":"2023-11-24T16:16:39.025+08:00[Asia/Shanghai]","screenshots":[{"screenshot":"34ae0d05eebae2ace7c4a8fd3c12de7241225111d036559d2ff9ae5eebf75e7d.png","timeStamp":1700813799550},{"screenshot":"4ec8f0fd81c7b87a820c86f650c71cd84e058fec8886d856a325cb97db9fc1f6.png","timeStamp":1700813801656},{"screenshot":"4dab8377f2f3ff9e0b4c288ca4790578a856d6887e9e46a5fdfcb9503a8adc50.png","timeStamp":1700813803256}],"result":"SUCCESS","precondition":false,"level":0},{"number":47,"description":"When I click on \u0027Save\u0027 button","duration":446,"startTime":"2023-11-24T16:16:43.257+08:00[Asia/Shanghai]","screenshots":[{"screenshot":"e815a085d25c6e1b6567d8987628dd37795941d76a22730664ce40d1ec8d09ba.png","timeStamp":1700813803697},{"screenshot":"e815a085d25c6e1b6567d8987628dd37795941d76a22730664ce40d1ec8d09ba.png","timeStamp":1700813803703}],"result":"SUCCESS","precondition":false,"level":0},{"number":48,"description":"Then the voucher entry successfully created modal and its contents should show up","duration":20369,"startTime":"2023-11-24T16:16:43.704+08:00[Asia/Shanghai]","screenshots":[{"screenshot":"e815a085d25c6e1b6567d8987628dd37795941d76a22730664ce40d1ec8d09ba.png","timeStamp":1700813803709}],"result":"SUCCESS","precondition":false,"level":0,"children":[{"number":49,"description":"Then the voucher entry successfully created modal should show up","duration":20344,"startTime":"2023-11-24T16:16:43.711+08:00[Asia/Shanghai]","screenshots":[{"screenshot":"da456be9e95c13ad33e3558f7b81ffd3acc52fb947a017db2d604b011bb08d2b.png","htmlSource":"pagesource7159754584603024885.html.txt","timeStamp":1700813824053}],"exception":{"errorType":"org.openqa.selenium.TimeoutException","message":"Expected condition failed: waiting for visibility of element located by By.xpath: //div[contains(@class, \u0027modal\u0027) and contains(@style, \u0027left: 0px\u0027)]//h3 (tried for 20 second(s) with 100 milliseconds interval)","stackTrace":[{"declaringClass":"utils.ExplicitWait","methodName":"explicitlyWaitForVisibilityOfElement","fileName":"ExplicitWait.java","lineNumber":30},{"declaringClass":"pageobjects.IRIS.FAD.FADModalPage","methodName":"getModalTitle","fileName":"FADModalPage.java","lineNumber":21},{"declaringClass":"steps.IRIS.FAD.VoucherEntrySteps","methodName":"then_the_Voucher_Entry_Successfully_Created_modal_should_show_up","fileName":"VoucherEntrySteps.java","lineNumber":206},{"declaringClass":"steps.IRIS.FAD.VoucherEntrySteps","methodName":"then_the_Voucher_Entry_Successfully_Created_modal_and_its_contents_should_show_up","fileName":"VoucherEntrySteps.java","lineNumber":188},{"declaringClass":"org.icrc.fadapplic.IRIS.FAD.AccountsPayable.ReviewAPEntries","methodName":"createVoucherEntryAndEdit","fileName":"ReviewAPEntries.java","lineNumber":1129}],"rootCause":{"errorType":"org.openqa.selenium.NoSuchElementException","message":"no such element: Unable to locate element: {\"method\":\"xpath\",\"selector\":\"//div[contains(@class, \u0027modal\u0027) and contains(@style, \u0027left: 0px\u0027)]//h3\"}\n  (Session info: headless chrome\u003d119.0.6045.160)\nFor documentation on this error, please visit: https://www.seleniumhq.org/exceptions/no_such_element.html\nBuild info: version: \u00273.141.59\u0027, revision: \u0027e82be7d358\u0027, time: \u00272018-11-14T08:17:03\u0027\nSystem info: host: \u0027PCS15848\u0027, ip: \u0027192.168.55.102\u0027, os.name: \u0027Windows 10\u0027, os.arch: \u0027amd64\u0027, os.version: \u002710.0\u0027, java.version: \u00271.8.0_392\u0027\nDriver info: org.openqa.selenium.chrome.ChromeDriver\nCapabilities {acceptInsecureCerts: false, browserName: chrome, browserVersion: 119.0.6045.160, chrome: {chromedriverVersion: 119.0.6045.105 (38c72552c5e..., userDataDir: C:\\Users\\A734509\\AppData\\Lo...}, fedcm:accounts: true, goog:chromeOptions: {debuggerAddress: localhost:58123}, javascriptEnabled: true, networkConnectionEnabled: false, pageLoadStrategy: normal, platform: WINDOWS, platformName: WINDOWS, proxy: Proxy(), setWindowRect: true, strictFileInteractability: false, timeouts: {implicit: 0, pageLoad: 300000, script: 30000}, unhandledPromptBehavior: dismiss and notify, webauthn:extension:credBlob: true, webauthn:extension:largeBlob: true, webauthn:extension:minPinLength: true, webauthn:extension:prf: true, webauthn:virtualAuthenticators: true}\nSession ID: 23f09d2aac8a41435e7e7ddc9caf06de\n*** Element info: {Using\u003dxpath, value\u003d//div[contains(@class, \u0027modal\u0027) and contains(@style, \u0027left: 0px\u0027)]//h3}","stackTrace":[{"declaringClass":"utils.ExplicitWait","methodName":"explicitlyWaitForVisibilityOfElement","fileName":"ExplicitWait.java","lineNumber":30},{"declaringClass":"pageobjects.IRIS.FAD.FADModalPage","methodName":"getModalTitle","fileName":"FADModalPage.java","lineNumber":21},{"declaringClass":"steps.IRIS.FAD.VoucherEntrySteps","methodName":"then_the_Voucher_Entry_Successfully_Created_modal_should_show_up","fileName":"VoucherEntrySteps.java","lineNumber":206},{"declaringClass":"steps.IRIS.FAD.VoucherEntrySteps","methodName":"then_the_Voucher_Entry_Successfully_Created_modal_and_its_contents_should_show_up","fileName":"VoucherEntrySteps.java","lineNumber":188},{"declaringClass":"org.icrc.fadapplic.IRIS.FAD.AccountsPayable.ReviewAPEntries","methodName":"createVoucherEntryAndEdit","fileName":"ReviewAPEntries.java","lineNumber":1129}]}},"result":"ERROR","precondition":false,"level":1},{"number":50,"description":"Then the batch number from voucher entry successfully created modal should show up","duration":1,"startTime":"2023-11-24T16:17:04.060+08:00[Asia/Shanghai]","result":"SKIPPED","precondition":false,"level":1},{"number":51,"description":"Then the document number from voucher entry successfully created modal should show up","duration":0,"startTime":"2023-11-24T16:17:04.067+08:00[Asia/Shanghai]","result":"SKIPPED","precondition":false,"level":1}]},{"number":52,"description":"When i click on modal review button","duration":0,"startTime":"2023-11-24T16:17:04.078+08:00[Asia/Shanghai]","result":"SKIPPED","precondition":false,"level":0},{"number":53,"description":"When I select the first voucher entry","duration":0,"startTime":"2023-11-24T16:17:04.084+08:00[Asia/Shanghai]","result":"SKIPPED","precondition":false,"level":0},{"number":54,"description":"When I click on \u0027View Entries\u0027 button","duration":0,"startTime":"2023-11-24T16:17:04.090+08:00[Asia/Shanghai]","result":"SKIPPED","precondition":false,"level":0},{"number":55,"description":"Then the \u0027Voucher Entry\u0027 modal should show up","duration":0,"startTime":"2023-11-24T16:17:04.095+08:00[Asia/Shanghai]","result":"SKIPPED","precondition":false,"level":0},{"number":56,"description":"Then the Cost center of the first voucher entry in Voucher Entry modal should be set to \u0027KYI2100\u0027","duration":0,"startTime":"2023-11-24T16:17:04.102+08:00[Asia/Shanghai]","result":"SKIPPED","precondition":false,"level":0},{"number":57,"description":"Then the Account Number of the first voucher entry in Voucher Entry modal should be set to \u0027212100\u0027","duration":1,"startTime":"2023-11-24T16:17:04.107+08:00[Asia/Shanghai]","result":"SKIPPED","precondition":false,"level":0},{"number":58,"description":"Then the Amount of the first voucher entry in Voucher Entry modal should be set to \u00271500\u0027","duration":0,"startTime":"2023-11-24T16:17:04.113+08:00[Asia/Shanghai]","result":"SKIPPED","precondition":false,"level":0},{"number":59,"description":"When i close the modal","duration":0,"startTime":"2023-11-24T16:17:04.119+08:00[Asia/Shanghai]","result":"SKIPPED","precondition":false,"level":0}],"userStory":{"id":"org.icrc.fadapplic.IRIS.FAD.AccountsPayable.ReviewAPEntries","storyName":"Review AP entries","storyClassName":"org.icrc.fadapplic.IRIS.FAD.AccountsPayable.ReviewAPEntries","path":"FAD.AccountsPayable","type":"story"},"featureTag":{"name":"Accounts payable/Review AP entries","type":"story","displayName":"Accounts payable/Review AP entries"},"title":"Create voucher entry and edit","coreIssues":["VER02"],"tags":[{"name":"FAD/Accounts payable","type":"feature","displayName":"Accounts payable"},{"name":"FAD","type":"capability","displayName":"FAD"},{"name":"Accounts payable/Review AP entries","type":"story","displayName":"Review AP entries"}],"startTime":"2023-11-24T16:14:15.925+08:00[Asia/Shanghai]","duration":168196,"testFailureCause":{"errorType":"org.openqa.selenium.NoSuchElementException","message":"no such element: Unable to locate element: {\"method\":\"xpath\",\"selector\":\"//div[contains(@class, \u0027modal\u0027) and contains(@style, \u0027left: 0px\u0027)]//h3\"}\n  (Session info: headless chrome\u003d119.0.6045.160)\nFor documentation on this error, please visit: https://www.seleniumhq.org/exceptions/no_such_element.html\nBuild info: version: \u00273.141.59\u0027, revision: \u0027e82be7d358\u0027, time: \u00272018-11-14T08:17:03\u0027\nSystem info: host: \u0027PCS15848\u0027, ip: \u0027192.168.55.102\u0027, os.name: \u0027Windows 10\u0027, os.arch: \u0027amd64\u0027, os.version: \u002710.0\u0027, java.version: \u00271.8.0_392\u0027\nDriver info: org.openqa.selenium.chrome.ChromeDriver\nCapabilities {acceptInsecureCerts: false, browserName: chrome, browserVersion: 119.0.6045.160, chrome: {chromedriverVersion: 119.0.6045.105 (38c72552c5e..., userDataDir: C:\\Users\\A734509\\AppData\\Lo...}, fedcm:accounts: true, goog:chromeOptions: {debuggerAddress: localhost:58123}, javascriptEnabled: true, networkConnectionEnabled: false, pageLoadStrategy: normal, platform: WINDOWS, platformName: WINDOWS, proxy: Proxy(), setWindowRect: true, strictFileInteractability: false, timeouts: {implicit: 0, pageLoad: 300000, script: 30000}, unhandledPromptBehavior: dismiss and notify, webauthn:extension:credBlob: true, webauthn:extension:largeBlob: true, webauthn:extension:minPinLength: true, webauthn:extension:prf: true, webauthn:virtualAuthenticators: true}\nSession ID: 23f09d2aac8a41435e7e7ddc9caf06de\n*** Element info: {Using\u003dxpath, value\u003d//div[contains(@class, \u0027modal\u0027) and contains(@style, \u0027left: 0px\u0027)]//h3}\nFor documentation on this error, please visit: https://www.seleniumhq.org/exceptions/no_such_element.html\nBuild info: version: \u00273.141.59\u0027, revision: \u0027e82be7d358\u0027, time: \u00272018-11-14T08:17:03\u0027\nSystem info: host: \u0027PCS15848\u0027, ip: \u0027192.168.55.102\u0027, os.name: \u0027Windows 10\u0027, os.arch: \u0027amd64\u0027, os.version: \u002710.0\u0027, java.version: \u00271.8.0_392\u0027\nDriver info: driver.version: unknown","stackTrace":[{"declaringClass":"utils.ExplicitWait","methodName":"explicitlyWaitForVisibilityOfElement","fileName":"ExplicitWait.java","lineNumber":30},{"declaringClass":"pageobjects.IRIS.FAD.FADModalPage","methodName":"getModalTitle","fileName":"FADModalPage.java","lineNumber":21},{"declaringClass":"steps.IRIS.FAD.VoucherEntrySteps","methodName":"then_the_Voucher_Entry_Successfully_Created_modal_should_show_up","fileName":"VoucherEntrySteps.java","lineNumber":206},{"declaringClass":"steps.IRIS.FAD.VoucherEntrySteps","methodName":"then_the_Voucher_Entry_Successfully_Created_modal_and_its_contents_should_show_up","fileName":"VoucherEntrySteps.java","lineNumber":188},{"declaringClass":"org.icrc.fadapplic.IRIS.FAD.AccountsPayable.ReviewAPEntries","methodName":"createVoucherEntryAndEdit","fileName":"ReviewAPEntries.java","lineNumber":1129}]},"testFailureClassname":"org.openqa.selenium.NoSuchElementException","testFailureMessage":"no such element: Unable to locate element: {\"method\":\"xpath\",\"selector\":\"//div[contains(@class, \u0027modal\u0027) and contains(@style, \u0027left: 0px\u0027)]//h3\"}\n  (Session info: headless chrome\u003d119.0.6045.160)\nFor documentation on this error, please visit: https://www.seleniumhq.org/exceptions/no_such_element.html\nBuild info: version: \u00273.141.59\u0027, revision: \u0027e82be7d358\u0027, time: \u00272018-11-14T08:17:03\u0027\nSystem info: host: \u0027PCS15848\u0027, ip: \u0027192.168.55.102\u0027, os.name: \u0027Windows 10\u0027, os.arch: \u0027amd64\u0027, os.version: \u002710.0\u0027, java.version: \u00271.8.0_392\u0027\nDriver info: org.openqa.selenium.chrome.ChromeDriver\nCapabilities {acceptInsecureCerts: false, browserName: chrome, browserVersion: 119.0.6045.160, chrome: {chromedriverVersion: 119.0.6045.105 (38c72552c5e..., userDataDir: C:\\Users\\A734509\\AppData\\Lo...}, fedcm:accounts: true, goog:chromeOptions: {debuggerAddress: localhost:58123}, javascriptEnabled: true, networkConnectionEnabled: false, pageLoadStrategy: normal, platform: WINDOWS, platformName: WINDOWS, proxy: Proxy(), setWindowRect: true, strictFileInteractability: false, timeouts: {implicit: 0, pageLoad: 300000, script: 30000}, unhandledPromptBehavior: dismiss and notify, webauthn:extension:credBlob: true, webauthn:extension:largeBlob: true, webauthn:extension:minPinLength: true, webauthn:extension:prf: true, webauthn:virtualAuthenticators: true}\nSession ID: 23f09d2aac8a41435e7e7ddc9caf06de\n*** Element info: {Using\u003dxpath, value\u003d//div[contains(@class, \u0027modal\u0027) and contains(@style, \u0027left: 0px\u0027)]//h3}\nFor documentation on this error, please visit: https://www.seleniumhq.org/exceptions/no_such_element.html\nBuild info: version: \u00273.141.59\u0027, revision: \u0027e82be7d358\u0027, time: \u00272018-11-14T08:17:03\u0027\nSystem info: host: \u0027PCS15848\u0027, ip: \u0027192.168.55.102\u0027, os.name: \u0027Windows 10\u0027, os.arch: \u0027amd64\u0027, os.version: \u002710.0\u0027, java.version: \u00271.8.0_392\u0027\nDriver info: driver.version: unknown","testFailureSummary":"ERROR;org.openqa.selenium.NoSuchElementException;no such element: Unable to locate element: {\"method\":\"xpath\",\"selector\":\"//div[contains(@class, \u0027modal\u0027) and contains(@style, \u0027left: 0px\u0027)]//h3\"}\n  (Session info: headless chrome\u003d119.0.6045.160)\nFor documentation on this error, please visit: https://www.seleniumhq.org/exceptions/no_such_element.html\nBuild info: version: \u00273.141.59\u0027, revision: \u0027e82be7d358\u0027, time: \u00272018-11-14T08:17:03\u0027\nSystem info: host: \u0027PCS15848\u0027, ip: \u0027192.168.55.102\u0027, os.name: \u0027Windows 10\u0027, os.arch: \u0027amd64\u0027, os.version: \u002710.0\u0027, java.version: \u00271.8.0_392\u0027\nDriver info: org.openqa.selenium.chrome.ChromeDriver\nCapabilities {acceptInsecureCerts: false, browserName: chrome, browserVersion: 119.0.6045.160, chrome: {chromedriverVersion: 119.0.6045.105 (38c72552c5e..., userDataDir: C:\\Users\\A734509\\AppData\\Lo...}, fedcm:accounts: true, goog:chromeOptions: {debuggerAddress: localhost:58123}, javascriptEnabled: true, networkConnectionEnabled: false, pageLoadStrategy: normal, platform: WINDOWS, platformName: WINDOWS, proxy: Proxy(), setWindowRect: true, strictFileInteractability: false, timeouts: {implicit: 0, pageLoad: 300000, script: 30000}, unhandledPromptBehavior: dismiss and notify, webauthn:extension:credBlob: true, webauthn:extension:largeBlob: true, webauthn:extension:minPinLength: true, webauthn:extension:prf: true, webauthn:virtualAuthenticators: true}\nSession ID: 23f09d2aac8a41435e7e7ddc9caf06de\n*** Element info: {Using\u003dxpath, value\u003d//div[contains(@class, \u0027modal\u0027) and contains(@style, \u0027left: 0px\u0027)]//h3}\nFor documentation on this error, please visit: https://www.seleniumhq.org/exceptions/no_such_element.html\nBuild info: version: \u00273.141.59\u0027, revision: \u0027e82be7d358\u0027, time: \u00272018-11-14T08:17:03\u0027\nSystem info: host: \u0027PCS15848\u0027, ip: \u0027192.168.55.102\u0027, os.name: \u0027Windows 10\u0027, os.arch: \u0027amd64\u0027, os.version: \u002710.0\u0027, java.version: \u00271.8.0_392\u0027\nDriver info: driver.version: unknown;ExplicitWait.java","projectKey":"","annotatedResult":"ERROR","sessionId":"23f09d2aac8a41435e7e7ddc9caf06de","driver":"chrome","isManualTestingUpToDate":false,"manual":false,"testSource":"JUnit","result":"ERROR","issues":["VER02"]}