{"name":"voucherEntryExportCSVFile","id":"org.icrc.fadapplic.IRIS.FAD.AccountsPayable.VoucherEntries:voucherEntryExportCSVFile","testCaseName":"org.icrc.fadapplic.IRIS.FAD.AccountsPayable.VoucherEntries","testSteps":[{"number":1,"description":"Given that I\u0027m logged in to Voucher Entry page","duration":23146,"startTime":"2023-11-17T23:58:37.839+08:00[Asia/Shanghai]","screenshots":[{"screenshot":"42181d0c54bafc7f4e6a1cc2164f8d881d517bdcc84dc4b5a36b95ee2bcea7cc.png","timeStamp":1700236740985}],"result":"SUCCESS","precondition":false,"level":0,"children":[{"number":2,"description":"When i open FAD URL","duration":20847,"startTime":"2023-11-17T23:58:37.840+08:00[Asia/Shanghai]","screenshots":[{"screenshot":"300f9345ff2f1a4c540668fe4c1ddf3dc54898bca36f827849691598744d9152.png","timeStamp":1700236738687}],"result":"SUCCESS","precondition":false,"level":1},{"number":3,"description":"When i open page from sidebar menu: {Accounts Payable,Voucher Entries,Voucher Entry}","duration":2290,"startTime":"2023-11-17T23:58:58.689+08:00[Asia/Shanghai]","screenshots":[{"screenshot":"300f9345ff2f1a4c540668fe4c1ddf3dc54898bca36f827849691598744d9152.png","timeStamp":1700236738695},{"screenshot":"487c78fae8df785f1fbf34c7199ee78287bcc551fec8d0b354e2d5a4ab100b92.png","timeStamp":1700236739232},{"screenshot":"ce9683d36a31bac0af73518270eb4db19a81a9d95867e62dac63e7cab3737b64.png","timeStamp":1700236739716},{"screenshot":"549ae7703ea7bb26708b0cd4b40d63ea5825dba60279fae4242b0463eabd40a3.png","timeStamp":1700236740220},{"screenshot":"42181d0c54bafc7f4e6a1cc2164f8d881d517bdcc84dc4b5a36b95ee2bcea7cc.png","timeStamp":1700236740979}],"result":"SUCCESS","precondition":false,"level":1}]},{"number":4,"description":"Then the Payment Information form and its contents should show up","duration":255,"startTime":"2023-11-17T23:59:00.986+08:00[Asia/Shanghai]","screenshots":[{"screenshot":"42181d0c54bafc7f4e6a1cc2164f8d881d517bdcc84dc4b5a36b95ee2bcea7cc.png","timeStamp":1700236741241}],"result":"SUCCESS","precondition":false,"level":0},{"number":5,"description":"When I set the Supplier to \u0027133339\u0027","duration":3669,"startTime":"2023-11-17T23:59:01.242+08:00[Asia/Shanghai]","screenshots":[{"screenshot":"29af141a7ac54cf3e77f88ed7d18225a86c16a441fa2125e779969951f62cf7c.png","timeStamp":1700236743096},{"screenshot":"cf2c518b7d74bc09b230126a284c07434ee9e8ff033876becbd2617b85e8b27e.png","timeStamp":1700236744911}],"result":"SUCCESS","precondition":false,"level":0},{"number":6,"description":"When I set the \u0027Invoice Number\u0027 to \u0027t2obdIh9zG\u0027","duration":469,"startTime":"2023-11-17T23:59:04.912+08:00[Asia/Shanghai]","screenshots":[{"screenshot":"0788ac29a9e641b5a524d419cca47347dad213fe7ef28adfc59ca12aa0b1a33e.png","timeStamp":1700236745381}],"result":"SUCCESS","precondition":false,"level":0},{"number":7,"description":"When I set the Currency to \u0027USD\u0027","duration":3729,"startTime":"2023-11-17T23:59:05.382+08:00[Asia/Shanghai]","screenshots":[{"screenshot":"3562831714f7d90b8e326bdcb6309544bf49bc1add9007f6424ebcbba6f5b2c5.png","timeStamp":1700236748147},{"screenshot":"07844ad6a223fe319f8e88925cc9d072ce17e93edf78ee4afab6385c0d497e69.png","timeStamp":1700236749111}],"result":"SUCCESS","precondition":false,"level":0},{"number":8,"description":"When i click on continue button","duration":1428,"startTime":"2023-11-17T23:59:09.112+08:00[Asia/Shanghai]","screenshots":[{"screenshot":"0c449505bfa574e0fdfb40efcd2fae0ae368adc95aab0355a4bc24547cccde83.png","timeStamp":1700236749531},{"screenshot":"5722639c1574b4768e4e135287a87b31563ab4f15874167584896ce47e40b79f.png","timeStamp":1700236750540}],"result":"SUCCESS","precondition":false,"level":0},{"number":9,"description":"When I select the first Bank Account and click \u0027Submit\u0027 button if modal exist","duration":32549,"startTime":"2023-11-17T23:59:10.541+08:00[Asia/Shanghai]","screenshots":[{"screenshot":"53c16213bbf867492e710be35ab3b953bf5b6dbf663192b4be0a17d2c1c0e7df.png","timeStamp":1700236781166},{"screenshot":"2c5be72cb1dad1fe7214094d765096b936d6730e1bf1d79cf05b79b24cdcf7c8.png","timeStamp":1700236781601},{"screenshot":"12873e1e28f804ce33a9df058defcf80cdf71c769195b96e4d20cfd21cdad1d6.png","timeStamp":1700236783090}],"result":"SUCCESS","precondition":false,"level":0},{"number":10,"description":"When I set the Gross Amount to \u002715000\u0027","duration":3581,"startTime":"2023-11-17T23:59:43.091+08:00[Asia/Shanghai]","screenshots":[{"screenshot":"272b3fd7c85c113d77ae36d22e1f6d3f01fbdbe9a6922956d865bc542fc16848.png","timeStamp":1700236786672}],"result":"SUCCESS","precondition":false,"level":0},{"number":11,"description":"When i click on continue button","duration":1289,"startTime":"2023-11-17T23:59:46.673+08:00[Asia/Shanghai]","screenshots":[{"screenshot":"c8890e7d952ac3e1ee61782432df6da0d657a764d16a8452153186ca70344e11.png","timeStamp":1700236787110},{"screenshot":"8b41cb12e9f284aad659eeb331317954d68c3b91e5f261b634b5a2dd4665ddac.png","timeStamp":1700236787962}],"result":"SUCCESS","precondition":false,"level":0},{"number":12,"description":"Then the \u0027GL Distribution\u0027 form and its contents should show up","duration":213,"startTime":"2023-11-17T23:59:47.963+08:00[Asia/Shanghai]","screenshots":[{"screenshot":"d89eaa0335b321daebd2072207aa9fdc24065ef8bc8fd6f871c1f1b417f0a3ac.png","timeStamp":1700236788176}],"result":"SUCCESS","precondition":false,"level":0},{"number":13,"description":"When I fill up the last row line and balance the amount using Account Number: \u0027911000\u0027, Amount: \u003cPrevious balance amount\u003e, Line Description: \u0027Test\u0027, Employee: \u0027Taramarcaz\u0027, Cost Center: \u0027MAN5000\u0027, Gen Obj: \u0027AFGHAIGPREACT0\u0027, AOE: \u0027YAO-25005\u0027, Units: \u002710\u0027, Unit of Measure: \u00271\u0027 Project ID: \u0027F307\u0027","duration":91508,"startTime":"2023-11-17T23:59:48.177+08:00[Asia/Shanghai]","screenshots":[{"screenshot":"33fd182231a8f874bb2a12bfa7a1b270350854d4fe0da57668c578994b398dd4.png","timeStamp":1700236879685}],"result":"SUCCESS","precondition":false,"level":0,"children":[{"number":14,"description":"When I click the last \u0027Additional Lines\u0027 table row","duration":3609,"startTime":"2023-11-17T23:59:48.183+08:00[Asia/Shanghai]","screenshots":[{"screenshot":"6a3c02fab54c58cb4d1300dc8079c236db42bbffc8e252820309d90f8fc2650c.png","timeStamp":1700236788560},{"screenshot":"69fcb436918f2076a945ac4c10a0b45fc1a274824fa06a4911ff6f21579a71b6.png","timeStamp":1700236791792}],"result":"SUCCESS","precondition":false,"level":1},{"number":15,"description":"When I set the \u0027Account Number\u0027 to \u0027911000\u0027","duration":6331,"startTime":"2023-11-17T23:59:51.793+08:00[Asia/Shanghai]","screenshots":[{"screenshot":"69fcb436918f2076a945ac4c10a0b45fc1a274824fa06a4911ff6f21579a71b6.png","timeStamp":1700236791799},{"screenshot":"f4556ccf73bfc14239f8438d8676caa3806a8b26dfaebe5ca1ffd421252763b0.png","timeStamp":1700236793931},{"screenshot":"49e22b5de04a30c5615e9b040438f4c75d176dce18901bf5379ed5c006409cce.png","timeStamp":1700236798124}],"result":"SUCCESS","precondition":false,"level":1},{"number":16,"description":"When I set the \u0027Line Description\u0027 to \u0027Test\u0027","duration":3952,"startTime":"2023-11-17T23:59:58.125+08:00[Asia/Shanghai]","screenshots":[{"screenshot":"49e22b5de04a30c5615e9b040438f4c75d176dce18901bf5379ed5c006409cce.png","timeStamp":1700236798131},{"screenshot":"0439dc99a719a9153e99e8faf1691078a6c0443047ac17bc9c58626f431553f7.png","timeStamp":1700236802077}],"result":"SUCCESS","precondition":false,"level":1},{"number":17,"description":"When I set the \u0027Employee\u0027 to \u0027Taramarcaz\u0027","duration":8332,"startTime":"2023-11-18T00:00:02.078+08:00[Asia/Shanghai]","screenshots":[{"screenshot":"0439dc99a719a9153e99e8faf1691078a6c0443047ac17bc9c58626f431553f7.png","timeStamp":1700236802085},{"screenshot":"6570d616362ce4ec9c8724ffe7b5366d4a235d58ef2642f1632891e2cc07170c.png","timeStamp":1700236805047},{"screenshot":"a6a524276f5db3a8cded02737a18840e51f592807959318c9b649f4b2a84528b.png","timeStamp":1700236810410}],"result":"SUCCESS","precondition":false,"level":1},{"number":18,"description":"When I set the \u0027Amount\u0027 to \u002715000.00\u0027","duration":7602,"startTime":"2023-11-18T00:00:10.491+08:00[Asia/Shanghai]","screenshots":[{"screenshot":"bf15f0994aef6fd6925615b05f2d58efadeb6646424f0b2948a80e211d2f8a28.png","timeStamp":1700236810627},{"screenshot":"0b2d8989146b0d78bc80ca6fddc7e2522fdc35d2bd5834f3c2c4b77c153479b0.png","timeStamp":1700236818093}],"result":"SUCCESS","precondition":false,"level":1},{"number":19,"description":"When I set the \u0027Cost Center\u0027 to \u0027MAN5000\u0027","duration":6482,"startTime":"2023-11-18T00:00:18.094+08:00[Asia/Shanghai]","screenshots":[{"screenshot":"0b2d8989146b0d78bc80ca6fddc7e2522fdc35d2bd5834f3c2c4b77c153479b0.png","timeStamp":1700236818100},{"screenshot":"20711ccad06ed352a055db219aadaf9a86837d5ee1e872d5a47877155297101d.png","timeStamp":1700236820358},{"screenshot":"ff75f6ae0f84632210c8330a1c6f0223d043d590a2405d41449f0452bd60442b.png","timeStamp":1700236824576}],"result":"SUCCESS","precondition":false,"level":1},{"number":20,"description":"When I set the \u0027Gen Obj\u0027 to \u0027AFGHAIGPREACT0\u0027","duration":26264,"startTime":"2023-11-18T00:00:24.576+08:00[Asia/Shanghai]","screenshots":[{"screenshot":"ff75f6ae0f84632210c8330a1c6f0223d043d590a2405d41449f0452bd60442b.png","timeStamp":1700236824582},{"screenshot":"85b6fc9a1b82c0bc60479f4e93f717f067427343b7476bf0c016b748a45464b0.png","timeStamp":1700236846509},{"screenshot":"33bdd76a40caf09fdee051dffad249c08e2ca6687acf31ebfde7dde2f5822119.png","timeStamp":1700236850840}],"result":"SUCCESS","precondition":false,"level":1},{"number":21,"description":"When I click on \u0027Show Next\u0027 button","duration":3690,"startTime":"2023-11-18T00:00:50.841+08:00[Asia/Shanghai]","screenshots":[{"screenshot":"33bdd76a40caf09fdee051dffad249c08e2ca6687acf31ebfde7dde2f5822119.png","timeStamp":1700236850846},{"screenshot":"16d2189764326f2817931d8994798fd05d9d3524bf9926b7e0b758205d01390c.png","timeStamp":1700236851272},{"screenshot":"d1e3639c9ee29d9ff1c9291d026f79b3d47953bc057ebb0853a9a49aaf109038.png","timeStamp":1700236854531}],"result":"SUCCESS","precondition":false,"level":1},{"number":22,"description":"When I set the \u0027Units\u0027 to \u002710\u0027","duration":3942,"startTime":"2023-11-18T00:00:54.532+08:00[Asia/Shanghai]","screenshots":[{"screenshot":"d1e3639c9ee29d9ff1c9291d026f79b3d47953bc057ebb0853a9a49aaf109038.png","timeStamp":1700236854538},{"screenshot":"144d10e31ce6b442e3eb543669d411385cc5942fe202c43d3e4adc6ba1fbb984.png","timeStamp":1700236858474}],"result":"SUCCESS","precondition":false,"level":1},{"number":23,"description":"When I set the \u0027Unit of Measure\u0027 to \u00271\u0027","duration":7311,"startTime":"2023-11-18T00:00:58.475+08:00[Asia/Shanghai]","screenshots":[{"screenshot":"144d10e31ce6b442e3eb543669d411385cc5942fe202c43d3e4adc6ba1fbb984.png","timeStamp":1700236858482},{"screenshot":"dfff3cd48500d415164604cda40e2819882c36999324449fe45ac667ec4ee027.png","timeStamp":1700236861458},{"screenshot":"a5ba00db99250dec7d7eabc336b221e2245187020e73d71dd0b3dd993d38cc41.png","timeStamp":1700236865786}],"result":"SUCCESS","precondition":false,"level":1},{"number":24,"description":"When I set the \u0027AOE\u0027 to \u0027YAO-25005\u0027","duration":7218,"startTime":"2023-11-18T00:01:05.787+08:00[Asia/Shanghai]","screenshots":[{"screenshot":"a5ba00db99250dec7d7eabc336b221e2245187020e73d71dd0b3dd993d38cc41.png","timeStamp":1700236865794},{"screenshot":"2680e01e6f1cf46fa1ce3b2addccd73bdd43677f45355906b624f531c01da837.png","timeStamp":1700236868644},{"screenshot":"4d7f3ef9ed65fb8266b7ff1ec9267137fbfdf75212288e377d574b034e5d0349.png","timeStamp":1700236873005}],"result":"SUCCESS","precondition":false,"level":1},{"number":25,"description":"When I set the \u0027Project ID\u0027 to \u0027F307\u0027","duration":6248,"startTime":"2023-11-18T00:01:13.006+08:00[Asia/Shanghai]","screenshots":[{"screenshot":"4d7f3ef9ed65fb8266b7ff1ec9267137fbfdf75212288e377d574b034e5d0349.png","timeStamp":1700236873011},{"screenshot":"74a777c7b514da9fb8c622d9e2003853ab85a338d903cd65213c38058d72f47b.png","timeStamp":1700236875138},{"screenshot":"05b8c907167c6053004be6c5d3031f3c9b3a5a0c0a5847df8db5249900e7043b.png","timeStamp":1700236879254}],"result":"SUCCESS","precondition":false,"level":1},{"number":26,"description":"When I click on \u0027Show Previous\u0027 button","duration":425,"startTime":"2023-11-18T00:01:19.255+08:00[Asia/Shanghai]","screenshots":[{"screenshot":"05b8c907167c6053004be6c5d3031f3c9b3a5a0c0a5847df8db5249900e7043b.png","timeStamp":1700236879261},{"screenshot":"33fd182231a8f874bb2a12bfa7a1b270350854d4fe0da57668c578994b398dd4.png","timeStamp":1700236879674},{"screenshot":"33fd182231a8f874bb2a12bfa7a1b270350854d4fe0da57668c578994b398dd4.png","timeStamp":1700236879680}],"result":"SUCCESS","precondition":false,"level":1}]},{"number":27,"description":"When i click on export button","duration":447,"startTime":"2023-11-18T00:01:19.686+08:00[Asia/Shanghai]","screenshots":[{"screenshot":"e65e5ebacf9347b6462741cae6b4eb0ede3e5363675126964fc6470377065d90.png","timeStamp":1700236880127},{"screenshot":"e65e5ebacf9347b6462741cae6b4eb0ede3e5363675126964fc6470377065d90.png","timeStamp":1700236880133}],"result":"SUCCESS","precondition":false,"level":0},{"number":28,"description":"Then a file should be downloaded","duration":10188,"startTime":"2023-11-18T00:01:20.133+08:00[Asia/Shanghai]","screenshots":[{"screenshot":"e12197d0242bb087e6d4baa41b273f2899569c00512696bee9219adb125dedd5.png","timeStamp":1700236890321}],"result":"SUCCESS","precondition":false,"level":0},{"number":29,"description":"Then the first GL Distribution CSV file first line should contain: Account Number: \u0027X.911000\u0027, Amount: \u003cPrevious balance amount\u003e, Line Description: \u0027TEST\u0027, Employee: \u002731578\u0027, Cost Center: \u0027MAN5000\u0027, Gen Obj: \u0027AFGHAIGEACT0\u0027, AOE: \u0027YAO-25005\u0027, Purchase Order: \u0027\u0027\u0027, Units: \u002710\u0027, Unit of Measure: \u00271\u0027 Project ID: \u0027PJ000001\u0027, Line Ref: \u0027\u0027","duration":142,"startTime":"2023-11-18T00:01:30.322+08:00[Asia/Shanghai]","screenshots":[{"screenshot":"e12197d0242bb087e6d4baa41b273f2899569c00512696bee9219adb125dedd5.png","timeStamp":1700236890329}],"result":"SUCCESS","precondition":false,"level":0,"children":[{"number":30,"description":"Then the CSV file Account Number for row index \u00270\u0027 should be \u0027X.911000\u0027","duration":12,"startTime":"2023-11-18T00:01:30.336+08:00[Asia/Shanghai]","screenshots":[{"screenshot":"e12197d0242bb087e6d4baa41b273f2899569c00512696bee9219adb125dedd5.png","timeStamp":1700236890348}],"result":"SUCCESS","precondition":false,"level":1},{"number":31,"description":"Then the CSV file Line Description for row index \u00270\u0027 should be \u0027TEST\u0027","duration":54,"startTime":"2023-11-18T00:01:30.348+08:00[Asia/Shanghai]","screenshots":[{"screenshot":"e12197d0242bb087e6d4baa41b273f2899569c00512696bee9219adb125dedd5.png","htmlSource":"pagesource8549072716727913797.html.txt","timeStamp":1700236890401}],"exception":{"errorType":"org.junit.ComparisonFailure","message":"expected:\u003cT[EST]\u003e but was:\u003cT[est]\u003e","stackTrace":[{"declaringClass":"steps.IRIS.FAD.VoucherEntrySteps","methodName":"then_the_CSV_file_should_contain_line_description","fileName":"VoucherEntrySteps.java","lineNumber":478},{"declaringClass":"steps.IRIS.FAD.VoucherEntrySteps","methodName":"then_the_downloaded_GL_Distribution_CSV_file_first_line_should_contain","fileName":"VoucherEntrySteps.java","lineNumber":402},{"declaringClass":"org.icrc.fadapplic.IRIS.FAD.AccountsPayable.VoucherEntries","methodName":"voucherEntryExportCSVFile","fileName":"VoucherEntries.java","lineNumber":885}]},"result":"FAILURE","precondition":false,"level":1},{"number":32,"description":"Then the CSV file Amount for row index \u00270\u0027 should be \u002715000.00\u0027","duration":1,"startTime":"2023-11-18T00:01:30.407+08:00[Asia/Shanghai]","result":"SKIPPED","precondition":false,"level":1},{"number":33,"description":"Then the CSV file Employee for row index \u00270\u0027 should be \u002731578\u0027","duration":0,"startTime":"2023-11-18T00:01:30.413+08:00[Asia/Shanghai]","result":"SKIPPED","precondition":false,"level":1},{"number":34,"description":"Then the CSV file Cost Center for row index \u00270\u0027 should be \u0027MAN5000\u0027","duration":0,"startTime":"2023-11-18T00:01:30.420+08:00[Asia/Shanghai]","result":"SKIPPED","precondition":false,"level":1},{"number":35,"description":"Then the CSV file General OBJ for row index \u00270\u0027 should be \u0027AFGHAIGEACT0\u0027","duration":0,"startTime":"2023-11-18T00:01:30.425+08:00[Asia/Shanghai]","result":"SKIPPED","precondition":false,"level":1},{"number":36,"description":"Then the CSV file AOE for row index \u00270\u0027 should be \u0027YAO-25005\u0027","duration":1,"startTime":"2023-11-18T00:01:30.431+08:00[Asia/Shanghai]","result":"SKIPPED","precondition":false,"level":1},{"number":37,"description":"Then the CSV file Purchase Order for row index \u00270\u0027 should be \u0027\u0027","duration":0,"startTime":"2023-11-18T00:01:30.437+08:00[Asia/Shanghai]","result":"SKIPPED","precondition":false,"level":1},{"number":38,"description":"Then the CSV file Units for row index \u00270\u0027 should be \u002710\u0027","duration":0,"startTime":"2023-11-18T00:01:30.443+08:00[Asia/Shanghai]","result":"SKIPPED","precondition":false,"level":1},{"number":39,"description":"Then the CSV file Unit of Measure for row index \u00270\u0027 should be \u00271\u0027","duration":0,"startTime":"2023-11-18T00:01:30.448+08:00[Asia/Shanghai]","result":"SKIPPED","precondition":false,"level":1},{"number":40,"description":"Then the CSV file Project ID for row index \u00270\u0027 should be \u0027PJ000001\u0027","duration":0,"startTime":"2023-11-18T00:01:30.454+08:00[Asia/Shanghai]","result":"SKIPPED","precondition":false,"level":1},{"number":41,"description":"Then the CSV file Line ref for row index \u00270\u0027 should be \u0027\u0027","duration":0,"startTime":"2023-11-18T00:01:30.459+08:00[Asia/Shanghai]","result":"SKIPPED","precondition":false,"level":1}]},{"number":42,"description":"When I click on \u0027Save\u0027 button","duration":0,"startTime":"2023-11-18T00:01:30.469+08:00[Asia/Shanghai]","result":"SKIPPED","precondition":false,"level":0},{"number":43,"description":"Then the voucher entry successfully created modal and its contents should show up","duration":0,"startTime":"2023-11-18T00:01:30.474+08:00[Asia/Shanghai]","result":"SKIPPED","precondition":false,"level":0}],"userStory":{"id":"org.icrc.fadapplic.IRIS.FAD.AccountsPayable.VoucherEntries","storyName":"Voucher entries","storyClassName":"org.icrc.fadapplic.IRIS.FAD.AccountsPayable.VoucherEntries","path":"FAD.AccountsPayable","type":"story"},"featureTag":{"name":"Accounts payable/Voucher entries","type":"story","displayName":"Accounts payable/Voucher entries"},"title":"Voucher entry export CSV file","coreIssues":["VE07"],"tags":[{"name":"FAD/Accounts payable","type":"feature","displayName":"Accounts payable"},{"name":"FAD","type":"capability","displayName":"FAD"},{"name":"Accounts payable/Voucher entries","type":"story","displayName":"Voucher entries"}],"startTime":"2023-11-17T23:58:37.540+08:00[Asia/Shanghai]","duration":172935,"testFailureCause":{"errorType":"java.lang.AssertionError","message":"expected:\u003cT[EST]\u003e but was:\u003cT[est]\u003e","stackTrace":[{"declaringClass":"steps.IRIS.FAD.VoucherEntrySteps","methodName":"then_the_CSV_file_should_contain_line_description","fileName":"VoucherEntrySteps.java","lineNumber":478},{"declaringClass":"steps.IRIS.FAD.VoucherEntrySteps","methodName":"then_the_downloaded_GL_Distribution_CSV_file_first_line_should_contain","fileName":"VoucherEntrySteps.java","lineNumber":402},{"declaringClass":"org.icrc.fadapplic.IRIS.FAD.AccountsPayable.VoucherEntries","methodName":"voucherEntryExportCSVFile","fileName":"VoucherEntries.java","lineNumber":885}]},"testFailureClassname":"java.lang.AssertionError","testFailureMessage":"expected:\u003cT[EST]\u003e but was:\u003cT[est]\u003e","testFailureSummary":"FAILURE;java.lang.AssertionError;expected:\u003cT[EST]\u003e but was:\u003cT[est]\u003e;VoucherEntrySteps.java","projectKey":"","annotatedResult":"FAILURE","sessionId":"cbc3228b87c9f6569d0cae10454dd981","driver":"chrome","isManualTestingUpToDate":false,"manual":false,"testSource":"JUnit","result":"FAILURE","issues":["VE07"]}