{"name":"createSalaryAdvanceEntry","id":"org.icrc.fadapplic.IRIS.FAD.GeneralLedger.SalaryAdvance:createSalaryAdvanceEntry","testCaseName":"org.icrc.fadapplic.IRIS.FAD.GeneralLedger.SalaryAdvance","testSteps":[{"number":1,"description":"Given that I\u0027m logged in to \u0027Working Advances\u0027 page","duration":23011,"startTime":"2023-11-18T00:25:24.174+08:00[Asia/Shanghai]","screenshots":[{"screenshot":"049ad632dcb77f58a3c0419d43c89f164ef21d505ef84a88e6fc7d95468adef7.png","timeStamp":1700238347185}],"result":"SUCCESS","precondition":false,"level":0,"children":[{"number":2,"description":"When i open FAD URL","duration":18815,"startTime":"2023-11-18T00:25:24.175+08:00[Asia/Shanghai]","screenshots":[{"screenshot":"2dad46e21ed5a64adb53cdd6c747a125d617a6572cfce21e66048004697f4dbf.png","timeStamp":1700238342990}],"result":"SUCCESS","precondition":false,"level":1},{"number":3,"description":"When i open page from sidebar menu: {General Ledger,Salary Advance}","duration":4187,"startTime":"2023-11-18T00:25:42.990+08:00[Asia/Shanghai]","screenshots":[{"screenshot":"2dad46e21ed5a64adb53cdd6c747a125d617a6572cfce21e66048004697f4dbf.png","timeStamp":1700238342998},{"screenshot":"d334552bb7d7df67c47c8259077e844a7d2f40cfd20a76ce66c90848dc821c1d.png","timeStamp":1700238343504},{"screenshot":"28670126c5cd87b2dd894f2c6e539578bb073fa986123a582ecfeaac4babec35.png","timeStamp":1700238343970},{"screenshot":"049ad632dcb77f58a3c0419d43c89f164ef21d505ef84a88e6fc7d95468adef7.png","timeStamp":1700238347177}],"result":"SUCCESS","precondition":false,"level":1}]},{"number":4,"description":"Then the \u0027Working Advance Registration\u0027 page should show up","duration":3292,"startTime":"2023-11-18T00:25:47.185+08:00[Asia/Shanghai]","screenshots":[{"screenshot":"049ad632dcb77f58a3c0419d43c89f164ef21d505ef84a88e6fc7d95468adef7.png","timeStamp":1700238350477}],"result":"SUCCESS","precondition":false,"level":0},{"number":5,"description":"When I set the Currency to \u0027USD\u0027","duration":7019,"startTime":"2023-11-18T00:25:50.477+08:00[Asia/Shanghai]","screenshots":[{"screenshot":"523b3c4053e8c47add54b0f35f8d502399078ccec2ba995941564f38e64a9827.png","timeStamp":1700238353437},{"screenshot":"67a772e27c69d8170baa34a83498b86ce1c7fbcf999aed360104fdb230da1009.png","timeStamp":1700238357496}],"result":"SUCCESS","precondition":false,"level":0},{"number":6,"description":"When I set the Amount to \u00271000\u0027","duration":891,"startTime":"2023-11-18T00:25:57.496+08:00[Asia/Shanghai]","screenshots":[{"screenshot":"a57fd4da1df0ac77aadafdb581aac4ac2375fe71b92183c3859532bdfc890bb9.png","timeStamp":1700238358386}],"result":"SUCCESS","precondition":false,"level":0},{"number":7,"description":"When I set the Employee to \u0027Taramarcaz\u0027","duration":4996,"startTime":"2023-11-18T00:25:58.387+08:00[Asia/Shanghai]","screenshots":[{"screenshot":"5c870d18b241cf4408153d5f960f86cab24f7c999f75ab52a611c2489ffdc0a7.png","timeStamp":1700238361137},{"screenshot":"8fd088e427816b18afd0b3bea0def8cb8bffdc71c16dafb4daeb4c5909722ea6.png","timeStamp":1700238363382}],"result":"SUCCESS","precondition":false,"level":0},{"number":8,"description":"When I set the Line Ref to \u0027TEST1\u0027","duration":618,"startTime":"2023-11-18T00:26:03.383+08:00[Asia/Shanghai]","screenshots":[{"screenshot":"368a8333e8f5e4871bb0edadfea0872195ed9adb0d8292793e35293b9c95c579.png","timeStamp":1700238364001}],"result":"SUCCESS","precondition":false,"level":0},{"number":9,"description":"When  I click \u0027Select Cash\u0027 button","duration":469,"startTime":"2023-11-18T00:26:04.002+08:00[Asia/Shanghai]","screenshots":[{"screenshot":"685f96769197b3b8c036c30becda9157375c53860af5a648e448b7f3c5abad01.png","timeStamp":1700238364464},{"screenshot":"685f96769197b3b8c036c30becda9157375c53860af5a648e448b7f3c5abad01.png","timeStamp":1700238364471}],"result":"SUCCESS","precondition":false,"level":0},{"number":10,"description":"When I select the checkbox the first cash account row","duration":31060,"startTime":"2023-11-18T00:26:04.472+08:00[Asia/Shanghai]","screenshots":[{"screenshot":"5a7bfb2502d5b1db7cfe3261e74ee6d7dd73ea01eb3e6b87b8d192239ea23a98.png","timeStamp":1700238395526},{"screenshot":"5a7bfb2502d5b1db7cfe3261e74ee6d7dd73ea01eb3e6b87b8d192239ea23a98.png","timeStamp":1700238395532}],"result":"SUCCESS","precondition":false,"level":0},{"number":11,"description":"When I click \u0027Submit\u0027 button","duration":500,"startTime":"2023-11-18T00:26:35.532+08:00[Asia/Shanghai]","screenshots":[{"screenshot":"6efd13b33f68cf2e010062004b0906fab088dee4c51d6cd4526fa6617bb09c78.png","timeStamp":1700238396025},{"screenshot":"6efd13b33f68cf2e010062004b0906fab088dee4c51d6cd4526fa6617bb09c78.png","timeStamp":1700238396032}],"result":"SUCCESS","precondition":false,"level":0},{"number":12,"description":"When I click \u0027Proceed\u0027 button","duration":3503,"startTime":"2023-11-18T00:26:36.032+08:00[Asia/Shanghai]","screenshots":[{"screenshot":"230c43d5f7f7c3d00d9549fbce03fa6ccbdc6fa55b28339c0b5aad3a95f7a43f.png","timeStamp":1700238396503},{"screenshot":"7cd393637e9cae53647821ba1ed0f47ccdc3927e823ca5039ee21e8a32d498b0.png","timeStamp":1700238399535}],"result":"SUCCESS","precondition":false,"level":0},{"number":13,"description":"Then the WAE successfully created modal should show up","duration":3304,"startTime":"2023-11-18T00:26:39.536+08:00[Asia/Shanghai]","screenshots":[{"screenshot":"c5ad44531b88fe1324016407d967ab275dc1de72f493537bca5a7c2de5742c16.png","timeStamp":1700238402840}],"result":"SUCCESS","precondition":false,"level":0}],"userStory":{"id":"org.icrc.fadapplic.IRIS.FAD.GeneralLedger.SalaryAdvance","storyName":"Salary advance","storyClassName":"org.icrc.fadapplic.IRIS.FAD.GeneralLedger.SalaryAdvance","path":"FAD.GeneralLedger","type":"story"},"featureTag":{"name":"General ledger/Salary advance","type":"story","displayName":"General ledger/Salary advance"},"title":"Create salary advance entry","tags":[{"name":"FAD","type":"capability","displayName":"FAD"},{"name":"General ledger/Salary advance","type":"story","displayName":"Salary advance"},{"name":"FAD/General ledger","type":"feature","displayName":"General ledger"}],"startTime":"2023-11-18T00:25:23.972+08:00[Asia/Shanghai]","duration":78868,"projectKey":"","sessionId":"531464f6782703616a0d04d20f71b225","driver":"chrome","isManualTestingUpToDate":false,"manual":false,"testSource":"JUnit","result":"SUCCESS"}