{"name":"manualPaymentWithMultipleDocuments","id":"org.icrc.fadapplic.IRIS.FAD.AccountsPayable.Payments:manualPaymentWithMultipleDocuments","testCaseName":"org.icrc.fadapplic.IRIS.FAD.AccountsPayable.Payments","testSteps":[{"number":1,"description":"Given that I\u0027m logged in to Voucher Entry page","duration":34081,"startTime":"2023-11-17T21:30:55.490+08:00[Asia/Shanghai]","screenshots":[{"screenshot":"85032831e60c88cd14aaf3b46cfee12aedd75c048a5c69b500eba969ea75b46c.png","timeStamp":1700227889571}],"result":"SUCCESS","precondition":false,"level":0,"children":[{"number":2,"description":"When i open FAD URL","duration":27600,"startTime":"2023-11-17T21:30:55.491+08:00[Asia/Shanghai]","screenshots":[{"screenshot":"1cb2fdccc4a8845b3ac38ec073848ebc6539849444692ea02f9d776f5ea26021.png","timeStamp":1700227883091}],"result":"SUCCESS","precondition":false,"level":1},{"number":3,"description":"When i open page from sidebar menu: {Accounts Payable,Voucher Entries,Voucher Entry}","duration":6471,"startTime":"2023-11-17T21:31:23.093+08:00[Asia/Shanghai]","screenshots":[{"screenshot":"1cb2fdccc4a8845b3ac38ec073848ebc6539849444692ea02f9d776f5ea26021.png","timeStamp":1700227883101},{"screenshot":"12b5f70fed4f0006b8ba96bb7f206fdc0e7a1d41d953cfb6f2d222043424f38a.png","timeStamp":1700227883643},{"screenshot":"b9c6c2a12cf7ecfe7ed43d3c812e1e3a1c8a78a2a42bca04e9d197a0613f8619.png","timeStamp":1700227884123},{"screenshot":"32f6c7557de12aa06849613da59916fc5d5363117511c476400a13ed1391fd72.png","timeStamp":1700227884666},{"screenshot":"85032831e60c88cd14aaf3b46cfee12aedd75c048a5c69b500eba969ea75b46c.png","timeStamp":1700227889564}],"result":"SUCCESS","precondition":false,"level":1}]},{"number":4,"description":"Then the Payment Information form and its contents should show up","duration":279,"startTime":"2023-11-17T21:31:29.571+08:00[Asia/Shanghai]","screenshots":[{"screenshot":"85032831e60c88cd14aaf3b46cfee12aedd75c048a5c69b500eba969ea75b46c.png","timeStamp":1700227889850}],"result":"SUCCESS","precondition":false,"level":0},{"number":5,"description":"When I set the Supplier to \u002726158\u0027","duration":6084,"startTime":"2023-11-17T21:31:29.850+08:00[Asia/Shanghai]","screenshots":[{"screenshot":"55b173ca7ad9cd7299a09870d119d59c1e67041faa476d0c1f7f3cd642672a3b.png","timeStamp":1700227891884},{"screenshot":"3529a28d778a00dc6a96eb73f925361e177852b7183295b3e4ff2b84ba58e66f.png","timeStamp":1700227895934}],"result":"SUCCESS","precondition":false,"level":0},{"number":6,"description":"When I set the \u0027Invoice Number\u0027 to \u0027MsULp53wWm\u0027","duration":466,"startTime":"2023-11-17T21:31:35.936+08:00[Asia/Shanghai]","screenshots":[{"screenshot":"07d50eb16c7e435a3cfeff7de6d059b2d817c4ef283f5af2ca6cfcffff2ae8cb.png","timeStamp":1700227896402}],"result":"SUCCESS","precondition":false,"level":0},{"number":7,"description":"When I set the Currency to \u0027EUR\u0027","duration":3865,"startTime":"2023-11-17T21:31:36.404+08:00[Asia/Shanghai]","screenshots":[{"screenshot":"2a7ab15b66bf7bc62089263c9f5c8192ec53585601b18b43aea8f2166bf5bef4.png","timeStamp":1700227899190},{"screenshot":"8dffbae254d88e3c5159f2b677332c03548a914b76de6d3cc28122505fda015b.png","timeStamp":1700227900269}],"result":"SUCCESS","precondition":false,"level":0},{"number":8,"description":"When i click on continue button","duration":1808,"startTime":"2023-11-17T21:31:40.270+08:00[Asia/Shanghai]","screenshots":[{"screenshot":"8cc74bc951b2e91614262703011a6208e6163b7635c11149cbfeff3cebfa1e28.png","timeStamp":1700227900690},{"screenshot":"cb5bec466d4bbb8aa08fd5c415f9288a112090864abf6f7c7ac973bac71e990b.png","timeStamp":1700227902078}],"result":"SUCCESS","precondition":false,"level":0},{"number":9,"description":"When I select the first Bank Account and click \u0027Submit\u0027 button if modal exist","duration":32669,"startTime":"2023-11-17T21:31:42.080+08:00[Asia/Shanghai]","screenshots":[{"screenshot":"49094efeb3454c05fd0ce72de864acb5004af3029a58bbd91ce9824b85589db1.png","timeStamp":1700227932789},{"screenshot":"ada38aa86c7944c10c08b18db53d659d737ab9ec1b3628108a38c56dde3a5caa.png","timeStamp":1700227933257},{"screenshot":"5ae55faeced22cd29b6c0b24967ee5cb02d08480d4d39d74e02091bc9f1fb043.png","timeStamp":1700227934748}],"result":"SUCCESS","precondition":false,"level":0},{"number":10,"description":"When I set the Gross Amount to \u002710000\u0027","duration":3928,"startTime":"2023-11-17T21:32:14.750+08:00[Asia/Shanghai]","screenshots":[{"screenshot":"c9e4683ffdb28adf781bcd26ccd08a3e1863bf50aa88768a57be0fbfee166985.png","timeStamp":1700227938678}],"result":"SUCCESS","precondition":false,"level":0},{"number":11,"description":"When i click on continue button","duration":2302,"startTime":"2023-11-17T21:32:18.680+08:00[Asia/Shanghai]","screenshots":[{"screenshot":"8128b818fa6275baa02509e616b42b02c0988f328566c821d6526ccac1d532c8.png","timeStamp":1700227939123},{"screenshot":"bb658c844661b4e710b4e90ec07da426abaa87a96bac8027bb4c9b1f6cb89878.png","timeStamp":1700227940982}],"result":"SUCCESS","precondition":false,"level":0},{"number":12,"description":"Then the \u0027GL Distribution\u0027 form and its contents should show up","duration":231,"startTime":"2023-11-17T21:32:20.984+08:00[Asia/Shanghai]","screenshots":[{"screenshot":"3608c4e92976128fa6270a7afe4ebfac9127b9038d8c092940a50c462bc10649.png","timeStamp":1700227941215}],"result":"SUCCESS","precondition":false,"level":0},{"number":13,"description":"When I set the Account Number to \u002791100\u0027","duration":6748,"startTime":"2023-11-17T21:32:21.216+08:00[Asia/Shanghai]","screenshots":[{"screenshot":"a07f390974d82f5994820e9d0ff39c493d18fbfe863b0c9f5db211498c7382bf.png","timeStamp":1700227943404},{"screenshot":"d47b6a31d33b8c951610ed8b2c0e039b3836e54642ef2d120e2810e5d5f74714.png","timeStamp":1700227947964}],"result":"SUCCESS","precondition":false,"level":0},{"number":14,"description":"When I set the Line Description to \u0027Test\u0027","duration":603,"startTime":"2023-11-17T21:32:27.965+08:00[Asia/Shanghai]","screenshots":[{"screenshot":"9c743edb2f8e932922c9022211ebce18cd3209f27578e53eed274c643277dc4e.png","timeStamp":1700227948567}],"result":"SUCCESS","precondition":false,"level":0},{"number":15,"description":"When I set the Amount to \u002710000\u0027","duration":4002,"startTime":"2023-11-17T21:32:28.568+08:00[Asia/Shanghai]","screenshots":[{"screenshot":"91bc0427a87b912f20855087467b6f69783c6c2ae4e4408d9ed3b621e681712a.png","timeStamp":1700227952570}],"result":"SUCCESS","precondition":false,"level":0},{"number":16,"description":"When I set the Employee to \u0027Milos Vitas\u0027","duration":7996,"startTime":"2023-11-17T21:32:32.570+08:00[Asia/Shanghai]","screenshots":[{"screenshot":"61d3e37c02192c2fcd2f524a0e41a7913fc3609e9169c1b13d9e71a40b464b9c.png","timeStamp":1700227955219},{"screenshot":"7fd396446e073c5cced5a63ce4b39bfc54c6c81b1aa64f4afe7e42b7baea60f9.png","timeStamp":1700227960566}],"result":"SUCCESS","precondition":false,"level":0},{"number":17,"description":"When I set the Cost Center to \u00271MAN400\u0027","duration":4032,"startTime":"2023-11-17T21:32:40.567+08:00[Asia/Shanghai]","screenshots":[{"screenshot":"fcc8836b91ca3f64a89153b64cf69aff314ae42fa64f7515376edaf6275ed0e0.png","timeStamp":1700227963484},{"screenshot":"13fa61b93ed46d013b8de906d12eebdb91d3337c4cc08512de307b49fcb3b1f3.png","timeStamp":1700227964598}],"result":"SUCCESS","precondition":false,"level":0},{"number":18,"description":"When I set the General Obj to \u0027AFGHAI\u0027","duration":3217,"startTime":"2023-11-17T21:32:44.600+08:00[Asia/Shanghai]","screenshots":[{"screenshot":"1234171c9a9f0213fb4311e5557dedebbc11ac827ae78653dfe587b8781979bb.png","timeStamp":1700227966701},{"screenshot":"1d989c3ec0e2eb7d6f2cc1d5404cf9f1039e618af8e6fce7122b6c469f86f3b1.png","timeStamp":1700227967817}],"result":"SUCCESS","precondition":false,"level":0},{"number":19,"description":"When I click on the \u0027Show Next\u0027 button","duration":419,"startTime":"2023-11-17T21:32:47.818+08:00[Asia/Shanghai]","screenshots":[{"screenshot":"693288c09248a832614e7d8cf083c9f3d7c35d554b39871c795172dbb847dbac.png","timeStamp":1700227968231},{"screenshot":"693288c09248a832614e7d8cf083c9f3d7c35d554b39871c795172dbb847dbac.png","timeStamp":1700227968237}],"result":"SUCCESS","precondition":false,"level":0},{"number":20,"description":"When I set the AOE to \u0027YAO\u0027","duration":3242,"startTime":"2023-11-17T21:32:48.238+08:00[Asia/Shanghai]","screenshots":[{"screenshot":"c8e82c8da2e750690573ac6d1a363dff774c31ff6a583701d69ac7c2906bf8b4.png","timeStamp":1700227970381},{"screenshot":"f996d2f0fb0a8ffc133f1872edc23ec8e1e681cee31604f7e9e741f834447d30.png","timeStamp":1700227971479}],"result":"SUCCESS","precondition":false,"level":0},{"number":21,"description":"When I set the Line Ref to \u0027Test123\u0027","duration":685,"startTime":"2023-11-17T21:32:51.481+08:00[Asia/Shanghai]","screenshots":[{"screenshot":"b035ebe9a9c751f303d9d37b3978609cec0807dce3a6f78bb0e49b366de81ae2.png","timeStamp":1700227972166}],"result":"SUCCESS","precondition":false,"level":0},{"number":22,"description":"When I set the Purchase Order to \u002712345\u0027","duration":614,"startTime":"2023-11-17T21:32:52.167+08:00[Asia/Shanghai]","screenshots":[{"screenshot":"1d89299843980d958297c7f1b36b12956c34e36569d89a1ce45370b8ab2d4887.png","timeStamp":1700227972781}],"result":"SUCCESS","precondition":false,"level":0},{"number":23,"description":"When I set the Units to \u002710\u0027","duration":649,"startTime":"2023-11-17T21:32:52.782+08:00[Asia/Shanghai]","screenshots":[{"screenshot":"92833780a01d20461525b988d8ebe9961decfbb0d7470711cb383df6bd29ee23.png","timeStamp":1700227973431}],"result":"SUCCESS","precondition":false,"level":0},{"number":24,"description":"When I set the Unit of Measure to \u002710\u0027","duration":3166,"startTime":"2023-11-17T21:32:53.433+08:00[Asia/Shanghai]","screenshots":[{"screenshot":"c476c7a766f4838d04418456405144a3b7a9fe6b140ece547931acff3b0d26ba.png","timeStamp":1700227975498},{"screenshot":"a754c624c00cfdfe63c9fbb2a79e0bb9f1d6ec9a2873f107caefcbdb34c595d0.png","timeStamp":1700227976599}],"result":"SUCCESS","precondition":false,"level":0},{"number":25,"description":"When I click on \u0027Save\u0027 button","duration":1933,"startTime":"2023-11-17T21:32:56.600+08:00[Asia/Shanghai]","screenshots":[{"screenshot":"e6d092c8400dacc574076c15f371d66eb040b328a5149a010568aa376d0b6167.png","timeStamp":1700227977036},{"screenshot":"3c0ea7a3d7b4709da4a9e43d5b8b08d1d90b102b457747d1e7886706c9c71da9.png","timeStamp":1700227978533}],"result":"SUCCESS","precondition":false,"level":0},{"number":26,"description":"Then the voucher entry successfully created modal and its contents should show up","duration":780,"startTime":"2023-11-17T21:32:58.534+08:00[Asia/Shanghai]","screenshots":[{"screenshot":"25ddb88e18683aad0c1683b1b64fc5f7e83db95b5acab3b5ed73af997db76123.png","timeStamp":1700227979314}],"result":"SUCCESS","precondition":false,"level":0,"children":[{"number":27,"description":"Then the voucher entry successfully created modal should show up","duration":241,"startTime":"2023-11-17T21:32:58.541+08:00[Asia/Shanghai]","screenshots":[{"screenshot":"589b794c74c1a320ece8eaaf6b1e600e52a1db435ccca09d2435c17ce0c031b7.png","timeStamp":1700227978782}],"result":"SUCCESS","precondition":false,"level":1},{"number":28,"description":"Then the batch number from voucher entry successfully created modal should show up","duration":260,"startTime":"2023-11-17T21:32:58.783+08:00[Asia/Shanghai]","screenshots":[{"screenshot":"589b794c74c1a320ece8eaaf6b1e600e52a1db435ccca09d2435c17ce0c031b7.png","timeStamp":1700227978790},{"screenshot":"21615251331e231f18c70a4e1e833dd8a94f45e3932c51678ea72c86ed5620fb.png","timeStamp":1700227979043}],"result":"SUCCESS","precondition":false,"level":1},{"number":29,"description":"Then the document number from voucher entry successfully created modal should show up","duration":263,"startTime":"2023-11-17T21:32:59.044+08:00[Asia/Shanghai]","screenshots":[{"screenshot":"21615251331e231f18c70a4e1e833dd8a94f45e3932c51678ea72c86ed5620fb.png","timeStamp":1700227979051},{"screenshot":"25ddb88e18683aad0c1683b1b64fc5f7e83db95b5acab3b5ed73af997db76123.png","timeStamp":1700227979307}],"result":"SUCCESS","precondition":false,"level":1}]},{"number":30,"description":"When i click on new batch button","duration":445,"startTime":"2023-11-17T21:32:59.315+08:00[Asia/Shanghai]","screenshots":[{"screenshot":"065248455131598e1b2ac422a3f5d0dcd978980193d567b4c43cccbbff7f3362.png","timeStamp":1700227979752},{"screenshot":"065248455131598e1b2ac422a3f5d0dcd978980193d567b4c43cccbbff7f3362.png","timeStamp":1700227979760}],"result":"SUCCESS","precondition":false,"level":0},{"number":31,"description":"Then the Payment Information form and its contents should show up","duration":294,"startTime":"2023-11-17T21:32:59.761+08:00[Asia/Shanghai]","screenshots":[{"screenshot":"7e466bf5f286e448db43107fe733da513cbb87fb1835994c762ee6cdbd5329ac.png","timeStamp":1700227980055}],"result":"SUCCESS","precondition":false,"level":0},{"number":32,"description":"When I set the Supplier to \u0027118173\u0027","duration":3541,"startTime":"2023-11-17T21:33:00.056+08:00[Asia/Shanghai]","screenshots":[{"screenshot":"d3c5e75f122f81831caf6ba480869c1711077c27f1582c2c3dd3fe3167ab65e0.png","timeStamp":1700227981896},{"screenshot":"6c6c2cf83149e0cda2959f27ff0a7a449076a17a8d75b65b7d66ff2da14613e0.png","timeStamp":1700227983597}],"result":"SUCCESS","precondition":false,"level":0},{"number":33,"description":"When I set the \u0027Invoice Number\u0027 to \u0027IUuY359AnH\u0027","duration":485,"startTime":"2023-11-17T21:33:03.598+08:00[Asia/Shanghai]","screenshots":[{"screenshot":"17aedbaf4bc403c90aa188a433a2c65173fe151068efd8f784bb632f1eeb85d8.png","timeStamp":1700227984083}],"result":"SUCCESS","precondition":false,"level":0},{"number":34,"description":"When I set the Currency to \u0027EUR\u0027","duration":123218,"startTime":"2023-11-17T21:33:04.084+08:00[Asia/Shanghai]","screenshots":[{"screenshot":"78c214260098b563b979dbc3e375a155bdeccc4affd1d29577aa7c935398b8d3.png","htmlSource":"pagesource2299830636290289747.html.txt","timeStamp":1700228107299}],"exception":{"errorType":"org.openqa.selenium.TimeoutException","message":"Expected condition failed: waiting for visibility of all elements located by By.xpath:  .//div[contains(@class, \u0027form-item\u0027)][span[text()\u003d\u0027Currency\u0027]]//div[contains(@class, \u0027Select-option\u0027)] | .//div[contains(@class, \u0027form-item\u0027)][span[contains(text(), \u0027Currency\u0027)]]//div[contains(@class, \u0027Select-option\u0027)] (tried for 120 second(s) with 100 milliseconds interval)\nBuild info: version: \u00273.141.59\u0027, revision: \u0027e82be7d358\u0027, time: \u00272018-11-14T08:17:03\u0027\nSystem info: host: \u0027PCS15848\u0027, ip: \u0027192.168.55.101\u0027, os.name: \u0027Windows 10\u0027, os.arch: \u0027amd64\u0027, os.version: \u002710.0\u0027, java.version: \u00271.8.0_392\u0027\nDriver info: net.thucydides.core.webdriver.WebDriverFacade","stackTrace":[{"declaringClass":"utils.ExplicitWait","methodName":"explicitlyWaitForVisibilityOfAllElements","fileName":"ExplicitWait.java","lineNumber":94},{"declaringClass":"pageobjects.IRIS.FAD.FADGenericPage","methodName":"selectDropdownOption","fileName":"FADGenericPage.java","lineNumber":80},{"declaringClass":"pageobjects.IRIS.FAD.FADGenericPage","methodName":"selectDropdownOption","fileName":"FADGenericPage.java","lineNumber":116},{"declaringClass":"pageobjects.IRIS.FAD.FADGenericPage","methodName":"typeAndSelectLabeledDropdownOption","fileName":"FADGenericPage.java","lineNumber":200},{"declaringClass":"pageobjects.IRIS.FAD.FADGenericPage","methodName":"setCurrency","fileName":"FADGenericPage.java","lineNumber":279},{"declaringClass":"steps.IRIS.FAD.VoucherEntrySteps","methodName":"when_I_select_the_Currency","fileName":"VoucherEntrySteps.java","lineNumber":49},{"declaringClass":"org.icrc.fadapplic.IRIS.FAD.AccountsPayable.Payments","methodName":"manualPaymentWithMultipleDocuments","fileName":"Payments.java","lineNumber":1214}]},"result":"ERROR","precondition":false,"level":0},{"number":35,"description":"When i click on continue button","duration":1,"startTime":"2023-11-17T21:35:07.308+08:00[Asia/Shanghai]","result":"SKIPPED","precondition":false,"level":0},{"number":36,"description":"When I select the first Bank Account and click \u0027Submit\u0027 button if modal exist","duration":1,"startTime":"2023-11-17T21:35:07.314+08:00[Asia/Shanghai]","result":"SKIPPED","precondition":false,"level":0},{"number":37,"description":"When I set the Gross Amount to \u002710000\u0027","duration":0,"startTime":"2023-11-17T21:35:07.321+08:00[Asia/Shanghai]","result":"SKIPPED","precondition":false,"level":0},{"number":38,"description":"When i click on continue button","duration":1,"startTime":"2023-11-17T21:35:07.326+08:00[Asia/Shanghai]","result":"SKIPPED","precondition":false,"level":0},{"number":39,"description":"Then the \u0027GL Distribution\u0027 form and its contents should show up","duration":0,"startTime":"2023-11-17T21:35:07.332+08:00[Asia/Shanghai]","result":"SKIPPED","precondition":false,"level":0},{"number":40,"description":"When I set the Account Number to \u002791100\u0027","duration":1,"startTime":"2023-11-17T21:35:07.337+08:00[Asia/Shanghai]","result":"SKIPPED","precondition":false,"level":0},{"number":41,"description":"When I set the Line Description to \u0027Test\u0027","duration":0,"startTime":"2023-11-17T21:35:07.343+08:00[Asia/Shanghai]","result":"SKIPPED","precondition":false,"level":0},{"number":42,"description":"When I set the Amount to \u002710000\u0027","duration":0,"startTime":"2023-11-17T21:35:07.348+08:00[Asia/Shanghai]","result":"SKIPPED","precondition":false,"level":0},{"number":43,"description":"When I set the Employee to \u0027Milos Vitas\u0027","duration":1,"startTime":"2023-11-17T21:35:07.353+08:00[Asia/Shanghai]","result":"SKIPPED","precondition":false,"level":0},{"number":44,"description":"When I set the Cost Center to \u00271MAN400\u0027","duration":0,"startTime":"2023-11-17T21:35:07.359+08:00[Asia/Shanghai]","result":"SKIPPED","precondition":false,"level":0},{"number":45,"description":"When I set the General Obj to \u0027AFGHAI\u0027","duration":0,"startTime":"2023-11-17T21:35:07.364+08:00[Asia/Shanghai]","result":"SKIPPED","precondition":false,"level":0},{"number":46,"description":"When I click on the \u0027Show Next\u0027 button","duration":1,"startTime":"2023-11-17T21:35:07.369+08:00[Asia/Shanghai]","result":"SKIPPED","precondition":false,"level":0},{"number":47,"description":"When I set the AOE to \u0027YAO\u0027","duration":0,"startTime":"2023-11-17T21:35:07.376+08:00[Asia/Shanghai]","result":"SKIPPED","precondition":false,"level":0},{"number":48,"description":"When I set the Line Ref to \u0027Test123\u0027","duration":0,"startTime":"2023-11-17T21:35:07.382+08:00[Asia/Shanghai]","result":"SKIPPED","precondition":false,"level":0},{"number":49,"description":"When I set the Purchase Order to \u002712345\u0027","duration":0,"startTime":"2023-11-17T21:35:07.388+08:00[Asia/Shanghai]","result":"SKIPPED","precondition":false,"level":0},{"number":50,"description":"When I set the Units to \u002710\u0027","duration":1,"startTime":"2023-11-17T21:35:07.393+08:00[Asia/Shanghai]","result":"SKIPPED","precondition":false,"level":0},{"number":51,"description":"When I set the Unit of Measure to \u002710\u0027","duration":0,"startTime":"2023-11-17T21:35:07.399+08:00[Asia/Shanghai]","result":"SKIPPED","precondition":false,"level":0},{"number":52,"description":"When I click on \u0027Save\u0027 button","duration":0,"startTime":"2023-11-17T21:35:07.404+08:00[Asia/Shanghai]","result":"SKIPPED","precondition":false,"level":0},{"number":53,"description":"Then the voucher entry successfully created modal and its contents should show up","duration":0,"startTime":"2023-11-17T21:35:07.410+08:00[Asia/Shanghai]","result":"SKIPPED","precondition":false,"level":0},{"number":54,"description":"When i click on proceed to payment button","duration":1,"startTime":"2023-11-17T21:35:07.415+08:00[Asia/Shanghai]","result":"SKIPPED","precondition":false,"level":0},{"number":55,"description":"Then that \u0027Manual Payment\u0027 page and its contents should show up","duration":1,"startTime":"2023-11-17T21:35:07.420+08:00[Asia/Shanghai]","result":"SKIPPED","precondition":false,"level":0},{"number":56,"description":"When I set the \u0027Supplier\u0027 to \u002726158\u0027","duration":0,"startTime":"2023-11-17T21:35:07.426+08:00[Asia/Shanghai]","result":"SKIPPED","precondition":false,"level":0},{"number":57,"description":"When I set the Invoice Number to \u0027MsULp53wWm\u0027","duration":0,"startTime":"2023-11-17T21:35:07.432+08:00[Asia/Shanghai]","result":"SKIPPED","precondition":false,"level":0},{"number":58,"description":"When I click on \u0027Search\u0027 button","duration":0,"startTime":"2023-11-17T21:35:07.437+08:00[Asia/Shanghai]","result":"SKIPPED","precondition":false,"level":0},{"number":59,"description":"Then the \u0027Open Invoices\u0027 section and its contents should show up","duration":0,"startTime":"2023-11-17T21:35:07.442+08:00[Asia/Shanghai]","result":"SKIPPED","precondition":false,"level":0},{"number":60,"description":"When I click the checkbox of the first enabled \u0027Open Invoices\u0027 row","duration":0,"startTime":"2023-11-17T21:35:07.447+08:00[Asia/Shanghai]","result":"SKIPPED","precondition":false,"level":0},{"number":61,"description":"When I click the \u0027Select Cash\u0027 button","duration":1,"startTime":"2023-11-17T21:35:07.452+08:00[Asia/Shanghai]","result":"SKIPPED","precondition":false,"level":0},{"number":62,"description":"Then the \u0027Select Cash Account\u0027 modal should show up","duration":0,"startTime":"2023-11-17T21:35:07.458+08:00[Asia/Shanghai]","result":"SKIPPED","precondition":false,"level":0},{"number":63,"description":"When I select the first account from \u0027Select cash account\u0027 modal","duration":1,"startTime":"2023-11-17T21:35:07.463+08:00[Asia/Shanghai]","result":"SKIPPED","precondition":false,"level":0},{"number":64,"description":"When I click the \u0027Submit\u0027 button from modal","duration":0,"startTime":"2023-11-17T21:35:07.469+08:00[Asia/Shanghai]","result":"SKIPPED","precondition":false,"level":0},{"number":65,"description":"Then the payment summary should appear","duration":0,"startTime":"2023-11-17T21:35:07.474+08:00[Asia/Shanghai]","result":"SKIPPED","precondition":false,"level":0},{"number":66,"description":"When I click on \u0027Proceed\u0027 button","duration":1,"startTime":"2023-11-17T21:35:07.478+08:00[Asia/Shanghai]","result":"SKIPPED","precondition":false,"level":0},{"number":67,"description":"Then the \u0027Manual Payment Successfully Created\u0027 modal should show up","duration":0,"startTime":"2023-11-17T21:35:07.484+08:00[Asia/Shanghai]","result":"SKIPPED","precondition":false,"level":0},{"number":68,"description":"When i click on modal continue button","duration":0,"startTime":"2023-11-17T21:35:07.490+08:00[Asia/Shanghai]","result":"SKIPPED","precondition":false,"level":0},{"number":69,"description":"Then that \u0027Manual Payment\u0027 page and its contents should show up","duration":0,"startTime":"2023-11-17T21:35:07.495+08:00[Asia/Shanghai]","result":"SKIPPED","precondition":false,"level":0},{"number":70,"description":"When I set the \u0027Supplier\u0027 to \u0027118173\u0027","duration":0,"startTime":"2023-11-17T21:35:07.500+08:00[Asia/Shanghai]","result":"SKIPPED","precondition":false,"level":0},{"number":71,"description":"When I set the Invoice Number to \u0027IUuY359AnH\u0027","duration":0,"startTime":"2023-11-17T21:35:07.505+08:00[Asia/Shanghai]","result":"SKIPPED","precondition":false,"level":0},{"number":72,"description":"When I click on \u0027Search\u0027 button","duration":0,"startTime":"2023-11-17T21:35:07.510+08:00[Asia/Shanghai]","result":"SKIPPED","precondition":false,"level":0},{"number":73,"description":"Then the \u0027Open Invoices\u0027 section and its contents should show up","duration":0,"startTime":"2023-11-17T21:35:07.515+08:00[Asia/Shanghai]","result":"SKIPPED","precondition":false,"level":0},{"number":74,"description":"When I click the checkbox of the first enabled \u0027Open Invoices\u0027 row","duration":1,"startTime":"2023-11-17T21:35:07.519+08:00[Asia/Shanghai]","result":"SKIPPED","precondition":false,"level":0},{"number":75,"description":"When I click the \u0027Select Cash\u0027 button","duration":1,"startTime":"2023-11-17T21:35:07.524+08:00[Asia/Shanghai]","result":"SKIPPED","precondition":false,"level":0},{"number":76,"description":"Then the \u0027Select Cash Account\u0027 modal should show up","duration":1,"startTime":"2023-11-17T21:35:07.529+08:00[Asia/Shanghai]","result":"SKIPPED","precondition":false,"level":0},{"number":77,"description":"When I select the first account from \u0027Select cash account\u0027 modal","duration":0,"startTime":"2023-11-17T21:35:07.534+08:00[Asia/Shanghai]","result":"SKIPPED","precondition":false,"level":0},{"number":78,"description":"When I click the \u0027Submit\u0027 button from modal","duration":0,"startTime":"2023-11-17T21:35:07.539+08:00[Asia/Shanghai]","result":"SKIPPED","precondition":false,"level":0},{"number":79,"description":"Then the payment summary should appear","duration":0,"startTime":"2023-11-17T21:35:07.545+08:00[Asia/Shanghai]","result":"SKIPPED","precondition":false,"level":0},{"number":80,"description":"When I click on \u0027Proceed\u0027 button","duration":0,"startTime":"2023-11-17T21:35:07.550+08:00[Asia/Shanghai]","result":"SKIPPED","precondition":false,"level":0},{"number":81,"description":"Then the \u0027Manual Payment Successfully Created\u0027 modal should show up","duration":1,"startTime":"2023-11-17T21:35:07.554+08:00[Asia/Shanghai]","result":"SKIPPED","precondition":false,"level":0},{"number":82,"description":"When i click on review payment button","duration":1,"startTime":"2023-11-17T21:35:07.559+08:00[Asia/Shanghai]","result":"SKIPPED","precondition":false,"level":0},{"number":83,"description":"Then the payment review search page should show up","duration":1,"startTime":"2023-11-17T21:35:07.564+08:00[Asia/Shanghai]","result":"SKIPPED","precondition":false,"level":0},{"number":84,"description":"When i clear the supplier field","duration":0,"startTime":"2023-11-17T21:35:07.570+08:00[Asia/Shanghai]","result":"SKIPPED","precondition":false,"level":0},{"number":85,"description":"When I click on \u0027Search\u0027 button","duration":0,"startTime":"2023-11-17T21:35:07.576+08:00[Asia/Shanghai]","result":"SKIPPED","precondition":false,"level":0},{"number":86,"description":"Then the documents for the previously processed payments should show up","duration":1,"startTime":"2023-11-17T21:35:07.581+08:00[Asia/Shanghai]","result":"SKIPPED","precondition":false,"level":0},{"number":87,"description":"Given that I\u0027m logged in to \u0027Batch Posting\u0027 page","duration":1,"startTime":"2023-11-17T21:35:07.587+08:00[Asia/Shanghai]","result":"SKIPPED","precondition":false,"level":0},{"number":88,"description":"When i click on clear button","duration":0,"startTime":"2023-11-17T21:35:07.593+08:00[Asia/Shanghai]","result":"SKIPPED","precondition":false,"level":0},{"number":89,"description":"When i set the batch type to all batches","duration":0,"startTime":"2023-11-17T21:35:07.599+08:00[Asia/Shanghai]","result":"SKIPPED","precondition":false,"level":0},{"number":90,"description":"When I set the Batch Number using the previously generated value","duration":0,"startTime":"2023-11-17T21:35:07.605+08:00[Asia/Shanghai]","result":"SKIPPED","precondition":false,"level":0},{"number":91,"description":"When I click \u0027Search\u0027 button","duration":0,"startTime":"2023-11-17T21:35:07.611+08:00[Asia/Shanghai]","result":"SKIPPED","precondition":false,"level":0},{"number":92,"description":"When I click \u0027See More\u0027 button","duration":0,"startTime":"2023-11-17T21:35:07.616+08:00[Asia/Shanghai]","result":"SKIPPED","precondition":false,"level":0},{"number":93,"description":"Then the batch should contains the previously created documents","duration":1,"startTime":"2023-11-17T21:35:07.623+08:00[Asia/Shanghai]","result":"SKIPPED","precondition":false,"level":0},{"number":94,"description":"When I click \u0027Post\u0027 button","duration":1,"startTime":"2023-11-17T21:35:07.629+08:00[Asia/Shanghai]","result":"SKIPPED","precondition":false,"level":0},{"number":95,"description":"Then the \u0027Batch Successfully Posted\u0027 notification message should show up","duration":1,"startTime":"2023-11-17T21:35:07.634+08:00[Asia/Shanghai]","result":"SKIPPED","precondition":false,"level":0}],"userStory":{"id":"org.icrc.fadapplic.IRIS.FAD.AccountsPayable.Payments","storyName":"Payments","storyClassName":"org.icrc.fadapplic.IRIS.FAD.AccountsPayable.Payments","path":"FAD.AccountsPayable","type":"story"},"featureTag":{"name":"Accounts payable/Payments","type":"story","displayName":"Accounts payable/Payments"},"title":"Manual payment with multiple documents","coreIssues":["MP07"],"tags":[{"name":"FAD/Accounts payable","type":"feature","displayName":"Accounts payable"},{"name":"FAD","type":"capability","displayName":"FAD"},{"name":"Accounts payable/Payments","type":"story","displayName":"Payments"}],"startTime":"2023-11-17T21:30:54.942+08:00[Asia/Shanghai]","duration":252696,"testFailureCause":{"errorType":"org.openqa.selenium.TimeoutException","message":"Expected condition failed: waiting for visibility of all elements located by By.xpath:  .//div[contains(@class, \u0027form-item\u0027)][span[text()\u003d\u0027Currency\u0027]]//div[contains(@class, \u0027Select-option\u0027)] | .//div[contains(@class, \u0027form-item\u0027)][span[contains(text(), \u0027Currency\u0027)]]//div[contains(@class, \u0027Select-option\u0027)] (tried for 120 second(s) with 100 milliseconds interval)\nBuild info: version: \u00273.141.59\u0027, revision: \u0027e82be7d358\u0027, time: \u00272018-11-14T08:17:03\u0027\nSystem info: host: \u0027PCS15848\u0027, ip: \u0027192.168.55.101\u0027, os.name: \u0027Windows 10\u0027, os.arch: \u0027amd64\u0027, os.version: \u002710.0\u0027, java.version: \u00271.8.0_392\u0027\nDriver info: net.thucydides.core.webdriver.WebDriverFacade\nBuild info: version: \u00273.141.59\u0027, revision: \u0027e82be7d358\u0027, time: \u00272018-11-14T08:17:03\u0027\nSystem info: host: \u0027PCS15848\u0027, ip: \u0027192.168.55.101\u0027, os.name: \u0027Windows 10\u0027, os.arch: \u0027amd64\u0027, os.version: \u002710.0\u0027, java.version: \u00271.8.0_392\u0027\nDriver info: driver.version: unknown","stackTrace":[{"declaringClass":"utils.ExplicitWait","methodName":"explicitlyWaitForVisibilityOfAllElements","fileName":"ExplicitWait.java","lineNumber":94},{"declaringClass":"pageobjects.IRIS.FAD.FADGenericPage","methodName":"selectDropdownOption","fileName":"FADGenericPage.java","lineNumber":80},{"declaringClass":"pageobjects.IRIS.FAD.FADGenericPage","methodName":"selectDropdownOption","fileName":"FADGenericPage.java","lineNumber":116},{"declaringClass":"pageobjects.IRIS.FAD.FADGenericPage","methodName":"typeAndSelectLabeledDropdownOption","fileName":"FADGenericPage.java","lineNumber":200},{"declaringClass":"pageobjects.IRIS.FAD.FADGenericPage","methodName":"setCurrency","fileName":"FADGenericPage.java","lineNumber":279},{"declaringClass":"steps.IRIS.FAD.VoucherEntrySteps","methodName":"when_I_select_the_Currency","fileName":"VoucherEntrySteps.java","lineNumber":49},{"declaringClass":"org.icrc.fadapplic.IRIS.FAD.AccountsPayable.Payments","methodName":"manualPaymentWithMultipleDocuments","fileName":"Payments.java","lineNumber":1214}]},"testFailureClassname":"org.openqa.selenium.TimeoutException","testFailureMessage":"Expected condition failed: waiting for visibility of all elements located by By.xpath:  .//div[contains(@class, \u0027form-item\u0027)][span[text()\u003d\u0027Currency\u0027]]//div[contains(@class, \u0027Select-option\u0027)] | .//div[contains(@class, \u0027form-item\u0027)][span[contains(text(), \u0027Currency\u0027)]]//div[contains(@class, \u0027Select-option\u0027)] (tried for 120 second(s) with 100 milliseconds interval)\nBuild info: version: \u00273.141.59\u0027, revision: \u0027e82be7d358\u0027, time: \u00272018-11-14T08:17:03\u0027\nSystem info: host: \u0027PCS15848\u0027, ip: \u0027192.168.55.101\u0027, os.name: \u0027Windows 10\u0027, os.arch: \u0027amd64\u0027, os.version: \u002710.0\u0027, java.version: \u00271.8.0_392\u0027\nDriver info: net.thucydides.core.webdriver.WebDriverFacade\nBuild info: version: \u00273.141.59\u0027, revision: \u0027e82be7d358\u0027, time: \u00272018-11-14T08:17:03\u0027\nSystem info: host: \u0027PCS15848\u0027, ip: \u0027192.168.55.101\u0027, os.name: \u0027Windows 10\u0027, os.arch: \u0027amd64\u0027, os.version: \u002710.0\u0027, java.version: \u00271.8.0_392\u0027\nDriver info: driver.version: unknown","testFailureSummary":"ERROR;org.openqa.selenium.TimeoutException;Expected condition failed: waiting for visibility of all elements located by By.xpath:  .//div[contains(@class, \u0027form-item\u0027)][span[text()\u003d\u0027Currency\u0027]]//div[contains(@class, \u0027Select-option\u0027)] | .//div[contains(@class, \u0027form-item\u0027)][span[contains(text(), \u0027Currency\u0027)]]//div[contains(@class, \u0027Select-option\u0027)] (tried for 120 second(s) with 100 milliseconds interval)\nBuild info: version: \u00273.141.59\u0027, revision: \u0027e82be7d358\u0027, time: \u00272018-11-14T08:17:03\u0027\nSystem info: host: \u0027PCS15848\u0027, ip: \u0027192.168.55.101\u0027, os.name: \u0027Windows 10\u0027, os.arch: \u0027amd64\u0027, os.version: \u002710.0\u0027, java.version: \u00271.8.0_392\u0027\nDriver info: net.thucydides.core.webdriver.WebDriverFacade\nBuild info: version: \u00273.141.59\u0027, revision: \u0027e82be7d358\u0027, time: \u00272018-11-14T08:17:03\u0027\nSystem info: host: \u0027PCS15848\u0027, ip: \u0027192.168.55.101\u0027, os.name: \u0027Windows 10\u0027, os.arch: \u0027amd64\u0027, os.version: \u002710.0\u0027, java.version: \u00271.8.0_392\u0027\nDriver info: driver.version: unknown;ExplicitWait.java","projectKey":"","annotatedResult":"ERROR","sessionId":"b359d3f0c3a967ff317f2c63d69e0854","driver":"chrome","isManualTestingUpToDate":false,"manual":false,"testSource":"JUnit","result":"ERROR","issues":["MP07"]}